{
  "DocumentMetadata": {
    "Pages": 1
  },
  "Blocks": [
    {
      "BlockType": "PAGE",
      "Geometry": {
        "BoundingBox": {
          "Width": 0.9348435401916504,
          "Height": 0.9399402737617493,
          "Left": 0.03840125352144241,
          "Top": 0.03423783928155899
        },
        "Polygon": [
          {
            "X": 0.041078463196754456,
            "Y": 0.03529238700866699
          },
          {
            "X": 0.9732447862625122,
            "Y": 0.03423783928155899
          },
          {
            "X": 0.9692990183830261,
            "Y": 0.97417813539505
          },
          {
            "X": 0.03840125352144241,
            "Y": 0.9630022048950195
          }
        ]
      },
      "Id": "13567174-f76b-427c-b067-94e3306c01c1",
      "Relationships": [
        {
          "Type": "CHILD",
          "Ids": [
            "df6eb9d3-959c-4561-81b2-099689bb6d80",
            "4e1734ef-257a-4178-bfc0-09aeef14be36",
            "faf4857f-582f-44ad-a78b-8b4212fa1c58",
            "8a002b7a-b0b6-4638-b172-4f16e2df5b69",
            "037c54fc-cba4-4132-a401-f979799f9b2b",
            "90e00f28-7eb1-4617-a61d-e30ad7d74d94",
            "c8230d20-d782-409e-9ba0-e401cf826a5a",
            "b9c85bab-fe48-465a-ae50-41f93cd35a1b",
            "07e88717-5871-48fb-940f-7f6dae9013ff",
            "6d586b88-7399-41a8-a794-525e820ed0e7",
            "42e0c8b8-fc81-46c0-a420-9156e9697dce"
          ]
        }
      ],
      "childText": "THE GOLDEN CROWN. A NEW AND CHOICE COLLECTION OF HYMNS AND TUNES, ORIGINAL AND SELECTED, FOR SABBATH SCHOOLS AND THE HOME CIRCLE. By H. T. MERRILL. \"O sing unto the Lord a new song.\"-Ps. 96: 1. CINCINNATI: PU-BLISHED BY JOHN CHURCH & CO., 66 WEST FOURTH STREET. ",
      "SearchKey": "THE GOLDEN CROWN. A NEW AND CHOICE COLLECTION OF HYMNS AND TUNES, ORIGINAL AND SELECTED, FOR SABBATH SCHOOLS AND THE HOME CIRCLE. By H. T. MERRILL. \"O sing unto the Lord a new song.\"-Ps. 96: 1. CINCINNATI: PU-BLISHED BY JOHN CHURCH & CO., 66 WEST FOURTH STREET. ",
      "Page": 1
    },
    {
      "BlockType": "LINE",
      "Confidence": 99.87274932861328,
      "Text": "THE",
      "Geometry": {
        "BoundingBox": {
          "Width": 0.08003715425729752,
          "Height": 0.02761603705585003,
          "Left": 0.46547001600265503,
          "Top": 0.0787106454372406
        },
        "Polygon": [
          {
            "X": 0.46556606888771057,
            "Y": 0.07875163853168488
          },
          {
            "X": 0.5455071926116943,
            "Y": 0.0787106454372406
          },
          {
            "X": 0.5454078912734985,
            "Y": 0.1063167080283165
          },
          {
            "X": 0.46547001600265503,
            "Y": 0.10632667690515518
          }
        ]
      },
      "Id": "df6eb9d3-959c-4561-81b2-099689bb6d80",
      "Relationships": [
        {
          "Type": "CHILD",
          "Ids": [
            "a17a526d-91ac-45fc-bb42-6cac73000dbe"
          ]
        }
      ],
      "Page": 1,
      "childText": "THE ",
      "SearchKey": "THE"
    },
    {
      "BlockType": "LINE",
      "Confidence": 75.7458724975586,
      "Text": "GOLDEN CROWN.",
      "Geometry": {
        "BoundingBox": {
          "Width": 0.7064990401268005,
          "Height": 0.06475889682769775,
          "Left": 0.1499522179365158,
          "Top": 0.15340915322303772
        },
        "Polygon": [
          {
            "X": 0.1501459777355194,
            "Y": 0.15340915322303772
          },
          {
            "X": 0.8564512729644775,
            "Y": 0.15379084646701813
          },
          {
            "X": 0.8561915755271912,
            "Y": 0.21816805005073547
          },
          {
            "X": 0.1499522179365158,
            "Y": 0.21714994311332703
          }
        ]
      },
      "Id": "4e1734ef-257a-4178-bfc0-09aeef14be36",
      "Relationships": [
        {
          "Type": "CHILD",
          "Ids": [
            "b72c4e9d-89cc-4f69-9bbe-4edd7a273798",
            "bd46724f-fbdc-493f-85bc-faf5a1d3c8be"
          ]
        }
      ],
      "Page": 1,
      "childText": "GOLDEN CROWN. ",
      "SearchKey": "GOLDEN CROWN."
    },
    {
      "BlockType": "LINE",
      "Confidence": 99.7857437133789,
      "Text": "A NEW AND CHOICE COLLECTION OF",
      "Geometry": {
        "BoundingBox": {
          "Width": 0.29936453700065613,
          "Height": 0.016676604747772217,
          "Left": 0.35337963700294495,
          "Top": 0.2636055052280426
        },
        "Polygon": [
          {
            "X": 0.3534328043460846,
            "Y": 0.2636055052280426
          },
          {
            "X": 0.6527441740036011,
            "Y": 0.26423177123069763
          },
          {
            "X": 0.6526840329170227,
            "Y": 0.2802821099758148
          },
          {
            "X": 0.35337963700294495,
            "Y": 0.2795884311199188
          }
        ]
      },
      "Id": "faf4857f-582f-44ad-a78b-8b4212fa1c58",
      "Relationships": [
        {
          "Type": "CHILD",
          "Ids": [
            "6ac81b5e-15f6-4058-b521-646f91cfa7f3",
            "cdf7839f-fe4b-444b-8651-dcf78d6b22e4",
            "76551f6e-4457-4ed3-9bac-9299d9cadc7d",
            "f265bdd7-6424-4529-a300-fef7e726df72",
            "18820092-db37-444a-a62b-df3abf2acede",
            "780d691f-6591-41d3-82f2-78293b25d540"
          ]
        }
      ],
      "Page": 1,
      "childText": "A NEW AND CHOICE COLLECTION OF ",
      "SearchKey": "A NEW AND CHOICE COLLECTION OF"
    },
    {
      "BlockType": "LINE",
      "Confidence": 99.51685333251953,
      "Text": "HYMNS AND TUNES,",
      "Geometry": {
        "BoundingBox": {
          "Width": 0.5856188535690308,
          "Height": 0.05111701413989067,
          "Left": 0.21147659420967102,
          "Top": 0.323142945766449
        },
        "Polygon": [
          {
            "X": 0.21162980794906616,
            "Y": 0.323142945766449
          },
          {
            "X": 0.7970954179763794,
            "Y": 0.3248627781867981
          },
          {
            "X": 0.7969002723693848,
            "Y": 0.37425994873046875
          },
          {
            "X": 0.21147659420967102,
            "Y": 0.37213507294654846
          }
        ]
      },
      "Id": "8a002b7a-b0b6-4638-b172-4f16e2df5b69",
      "Relationships": [
        {
          "Type": "CHILD",
          "Ids": [
            "7ded03dd-f0d3-48ce-ad14-b34e6ffdb5eb",
            "1a9ec00a-a7a3-463a-8745-e2d14fd4d1df",
            "04aa1a39-ec42-42f4-a2b0-c58120c5c48c"
          ]
        }
      ],
      "Page": 1,
      "childText": "HYMNS AND TUNES, ",
      "SearchKey": "HYMNS AND TUNES,"
    },
    {
      "BlockType": "LINE",
      "Confidence": 99.58208465576172,
      "Text": "ORIGINAL AND SELECTED, FOR",
      "Geometry": {
        "BoundingBox": {
          "Width": 0.24958011507987976,
          "Height": 0.02022498846054077,
          "Left": 0.3791116774082184,
          "Top": 0.4124174118041992
        },
        "Polygon": [
          {
            "X": 0.37917596101760864,
            "Y": 0.4124174118041992
          },
          {
            "X": 0.6286917924880981,
            "Y": 0.4134625792503357
          },
          {
            "X": 0.6286205649375916,
            "Y": 0.43264240026474
          },
          {
            "X": 0.3791116774082184,
            "Y": 0.43153008818626404
          }
        ]
      },
      "Id": "037c54fc-cba4-4132-a401-f979799f9b2b",
      "Relationships": [
        {
          "Type": "CHILD",
          "Ids": [
            "f29a6829-76a6-40d4-b560-b63e15072318",
            "c7aaa7de-ab50-4ee8-8373-7f6906b0a6f7",
            "e761e6e7-bbfb-4274-91b3-6ab86ea36ac5",
            "d9d57756-83f5-4e99-bfd3-ed9bbea082bc"
          ]
        }
      ],
      "Page": 1,
      "childText": "ORIGINAL AND SELECTED, FOR ",
      "SearchKey": "ORIGINAL AND SELECTED, FOR"
    },
    {
      "BlockType": "LINE",
      "Confidence": 99.36100769042969,
      "Text": "SABBATH SCHOOLS AND THE HOME CIRCLE.",
      "Geometry": {
        "BoundingBox": {
          "Width": 0.6319431066513062,
          "Height": 0.03249245882034302,
          "Left": 0.187910795211792,
          "Top": 0.4703132212162018
        },
        "Polygon": [
          {
            "X": 0.18800072371959686,
            "Y": 0.4703132212162018
          },
          {
            "X": 0.8198539018630981,
            "Y": 0.47348397970199585
          },
          {
            "X": 0.8197370767593384,
            "Y": 0.5028057098388672
          },
          {
            "X": 0.187910795211792,
            "Y": 0.4993756115436554
          }
        ]
      },
      "Id": "90e00f28-7eb1-4617-a61d-e30ad7d74d94",
      "Relationships": [
        {
          "Type": "CHILD",
          "Ids": [
            "dc1c323d-cf4f-4eb8-9ae6-b0641e1adb4b",
            "08538ef6-cc02-4a96-9ad6-3219053afc4f",
            "90363309-914e-42b1-850a-be9e83c959cd",
            "7b6edcf0-20a1-4d12-b44c-602d56c1eb39",
            "55c75503-34c8-48a2-8260-41981331730b",
            "dad1c89a-f25c-4148-af95-ef43bc29fe7e"
          ]
        }
      ],
      "Page": 1,
      "childText": "SABBATH SCHOOLS AND THE HOME CIRCLE. ",
      "SearchKey": "SABBATH SCHOOLS AND THE HOME CIRCLE."
    },
    {
      "BlockType": "LINE",
      "Confidence": 99.12129211425781,
      "Text": "By H. T. MERRILL.",
      "Geometry": {
        "BoundingBox": {
          "Width": 0.23055656254291534,
          "Height": 0.030836196616292,
          "Left": 0.3859429657459259,
          "Top": 0.5454996824264526
        },
        "Polygon": [
          {
            "X": 0.38604193925857544,
            "Y": 0.5454996824264526
          },
          {
            "X": 0.6164995431900024,
            "Y": 0.5468970537185669
          },
          {
            "X": 0.6163906455039978,
            "Y": 0.5763358473777771
          },
          {
            "X": 0.3859429657459259,
            "Y": 0.5748432278633118
          }
        ]
      },
      "Id": "c8230d20-d782-409e-9ba0-e401cf826a5a",
      "Relationships": [
        {
          "Type": "CHILD",
          "Ids": [
            "ff798630-4662-44c0-8d07-440fd9dee5ce",
            "f768cdf0-52b5-49df-b707-596bb4002ed3",
            "fe647522-6732-432a-8931-a4bea9e568c3",
            "516eaee0-e3ca-454f-95fd-5ebbf08353e6"
          ]
        }
      ],
      "Page": 1,
      "childText": "By H. T. MERRILL. ",
      "SearchKey": "By H. T. MERRILL."
    },
    {
      "BlockType": "LINE",
      "Confidence": 97.60796356201172,
      "Text": "\"O sing unto the Lord a new song.\"-Ps. 96: 1.",
      "Geometry": {
        "BoundingBox": {
          "Width": 0.3284847140312195,
          "Height": 0.022729113698005676,
          "Left": 0.33758124709129333,
          "Top": 0.6518044471740723
        },
        "Polygon": [
          {
            "X": 0.33764785528182983,
            "Y": 0.6518044471740723
          },
          {
            "X": 0.6660659313201904,
            "Y": 0.6542894840240479
          },
          {
            "X": 0.6659896373748779,
            "Y": 0.6745335459709167
          },
          {
            "X": 0.33758124709129333,
            "Y": 0.6719552874565125
          }
        ]
      },
      "Id": "b9c85bab-fe48-465a-ae50-41f93cd35a1b",
      "Relationships": [
        {
          "Type": "CHILD",
          "Ids": [
            "62427248-471c-4d1f-b10d-33acd56af15a",
            "e7744a51-aeef-4200-8fd9-d518415f03e4",
            "026be9a9-0bde-45ec-90f9-746c8852e18f",
            "30f3e2cb-b819-4086-a224-f25819ee43f6",
            "3abf5faa-29e7-4aea-9f88-4a60f3598558",
            "84272ffb-f535-4776-ab1c-e41d593c8d30",
            "588b5aa8-e595-40ea-b3d0-1060a024750e",
            "3199faa9-92f3-4206-97a2-a44b75af649d",
            "b246cc30-097a-4b84-8150-d56281637ff7",
            "09034c13-4ae6-49da-a838-74311901cd91"
          ]
        }
      ],
      "Page": 1,
      "childText": "\"O sing unto the Lord a new song.\"-Ps. 96: 1. ",
      "SearchKey": "\"O sing unto the Lord a new song.\"-Ps. 96: 1."
    },
    {
      "BlockType": "LINE",
      "Confidence": 95.89713287353516,
      "Text": "CINCINNATI:",
      "Geometry": {
        "BoundingBox": {
          "Width": 0.1974916160106659,
          "Height": 0.026002755388617516,
          "Left": 0.4030933380126953,
          "Top": 0.7531004548072815
        },
        "Polygon": [
          {
            "X": 0.4031754732131958,
            "Y": 0.7531004548072815
          },
          {
            "X": 0.6005849242210388,
            "Y": 0.7548745274543762
          },
          {
            "X": 0.6004958748817444,
            "Y": 0.7791032195091248
          },
          {
            "X": 0.4030933380126953,
            "Y": 0.7772620320320129
          }
        ]
      },
      "Id": "07e88717-5871-48fb-940f-7f6dae9013ff",
      "Relationships": [
        {
          "Type": "CHILD",
          "Ids": [
            "7621164c-1f39-4993-b463-7c434e08885b"
          ]
        }
      ],
      "Page": 1,
      "childText": "CINCINNATI: ",
      "SearchKey": "CINCINNATI:"
    },
    {
      "BlockType": "LINE",
      "Confidence": 91.298095703125,
      "Text": "PU-BLISHED BY JOHN CHURCH & CO.,",
      "Geometry": {
        "BoundingBox": {
          "Width": 0.516451895236969,
          "Height": 0.025165628641843796,
          "Left": 0.24174480140209198,
          "Top": 0.7837771773338318
        },
        "Polygon": [
          {
            "X": 0.2418086975812912,
            "Y": 0.7837771773338318
          },
          {
            "X": 0.7581966519355774,
            "Y": 0.7886521220207214
          },
          {
            "X": 0.7581175565719604,
            "Y": 0.8089428544044495
          },
          {
            "X": 0.24174480140209198,
            "Y": 0.8039211630821228
          }
        ]
      },
      "Id": "6d586b88-7399-41a8-a794-525e820ed0e7",
      "Relationships": [
        {
          "Type": "CHILD",
          "Ids": [
            "29bbbfec-6bf3-4842-952d-567cc51c1fba",
            "23ee0642-cd88-40ff-b11d-0ac5aed697ca",
            "5b8f95d6-bb20-4a49-af69-81b1b66d650e",
            "6a0549f0-03c4-4cb4-bf05-714d7fe1bce7",
            "9f86b129-1531-44c5-a34a-508e628ad9ad",
            "29fed303-6a93-4e22-932c-f01d5abc9f80"
          ]
        }
      ],
      "Page": 1,
      "childText": "PU-BLISHED BY JOHN CHURCH & CO., ",
      "SearchKey": "PU-BLISHED BY JOHN CHURCH & CO.,"
    },
    {
      "BlockType": "LINE",
      "Confidence": 98.85184478759766,
      "Text": "66 WEST FOURTH STREET.",
      "Geometry": {
        "BoundingBox": {
          "Width": 0.25678226351737976,
          "Height": 0.02212424762547016,
          "Left": 0.37010258436203003,
          "Top": 0.8160355687141418
        },
        "Polygon": [
          {
            "X": 0.3701680302619934,
            "Y": 0.8160355687141418
          },
          {
            "X": 0.6268848180770874,
            "Y": 0.8185714483261108
          },
          {
            "X": 0.6268121004104614,
            "Y": 0.8381598591804504
          },
          {
            "X": 0.37010258436203003,
            "Y": 0.8355534672737122
          }
        ]
      },
      "Id": "42e0c8b8-fc81-46c0-a420-9156e9697dce",
      "Relationships": [
        {
          "Type": "CHILD",
          "Ids": [
            "306b0b47-1f0f-418b-9ebc-4644740af7b4",
            "8a1f61b9-f997-439d-bd90-f7c03455f0ab",
            "ae2c7d9a-10de-4b24-8906-4b5880906e8c",
            "400e09e6-bf34-440d-9412-e398196c8970"
          ]
        }
      ],
      "Page": 1,
      "childText": "66 WEST FOURTH STREET. ",
      "SearchKey": "66 WEST FOURTH STREET."
    },
    {
      "BlockType": "WORD",
      "Confidence": 99.87274932861328,
      "Text": "THE",
      "TextType": "PRINTED",
      "Geometry": {
        "BoundingBox": {
          "Width": 0.08003715425729752,
          "Height": 0.02761603705585003,
          "Left": 0.46547001600265503,
          "Top": 0.0787106454372406
        },
        "Polygon": [
          {
            "X": 0.46556606888771057,
            "Y": 0.07875163853168488
          },
          {
            "X": 0.5455071926116943,
            "Y": 0.0787106454372406
          },
          {
            "X": 0.5454078912734985,
            "Y": 0.1063167080283165
          },
          {
            "X": 0.46547001600265503,
            "Y": 0.10632667690515518
          }
        ]
      },
      "Id": "a17a526d-91ac-45fc-bb42-6cac73000dbe",
      "Page": 1,
      "SearchKey": "THE"
    },
    {
      "BlockType": "WORD",
      "Confidence": 99.89624786376953,
      "Text": "GOLDEN",
      "TextType": "PRINTED",
      "Geometry": {
        "BoundingBox": {
          "Width": 0.34679868817329407,
          "Height": 0.06424040347337723,
          "Left": 0.1499522179365158,
          "Top": 0.15340915322303772
        },
        "Polygon": [
          {
            "X": 0.1501459777355194,
            "Y": 0.15340915322303772
          },
          {
            "X": 0.49675092101097107,
            "Y": 0.15359646081924438
          },
          {
            "X": 0.49652495980262756,
            "Y": 0.21764956414699554
          },
          {
            "X": 0.1499522179365158,
            "Y": 0.21714994311332703
          }
        ]
      },
      "Id": "b72c4e9d-89cc-4f69-9bbe-4edd7a273798",
      "Page": 1,
      "SearchKey": "GOLDEN"
    },
    {
      "BlockType": "WORD",
      "Confidence": 51.59550476074219,
      "Text": "CROWN.",
      "TextType": "PRINTED",
      "Geometry": {
        "BoundingBox": {
          "Width": 0.31485310196876526,
          "Height": 0.0635899007320404,
          "Left": 0.5415951013565063,
          "Top": 0.1543842852115631
        },
        "Polygon": [
          {
            "X": 0.5418218374252319,
            "Y": 0.1543842852115631
          },
          {
            "X": 0.8564481735229492,
            "Y": 0.15455769002437592
          },
          {
            "X": 0.8561923503875732,
            "Y": 0.21797418594360352
          },
          {
            "X": 0.5415951013565063,
            "Y": 0.2175215184688568
          }
        ]
      },
      "Id": "bd46724f-fbdc-493f-85bc-faf5a1d3c8be",
      "Page": 1,
      "SearchKey": "CROWN."
    },
    {
      "BlockType": "WORD",
      "Confidence": 99.81553649902344,
      "Text": "A",
      "TextType": "PRINTED",
      "Geometry": {
        "BoundingBox": {
          "Width": 0.011643239296972752,
          "Height": 0.015232374891638756,
          "Left": 0.35337963700294495,
          "Top": 0.264382928609848
        },
        "Polygon": [
          {
            "X": 0.35343021154403687,
            "Y": 0.264382928609848
          },
          {
            "X": 0.3650228679180145,
            "Y": 0.26440730690956116
          },
          {
            "X": 0.3649720251560211,
            "Y": 0.27961528301239014
          },
          {
            "X": 0.35337963700294495,
            "Y": 0.2795884311199188
          }
        ]
      },
      "Id": "6ac81b5e-15f6-4058-b521-646f91cfa7f3",
      "Page": 1,
      "SearchKey": "A"
    },
    {
      "BlockType": "WORD",
      "Confidence": 99.875244140625,
      "Text": "NEW",
      "TextType": "PRINTED",
      "Geometry": {
        "BoundingBox": {
          "Width": 0.03648803010582924,
          "Height": 0.015284674242138863,
          "Left": 0.3738522231578827,
          "Top": 0.26441875100135803
        },
        "Polygon": [
          {
            "X": 0.37390321493148804,
            "Y": 0.26441875100135803
          },
          {
            "X": 0.41034024953842163,
            "Y": 0.2644954025745392
          },
          {
            "X": 0.4102884531021118,
            "Y": 0.27970343828201294
          },
          {
            "X": 0.3738522231578827,
            "Y": 0.2796189785003662
          }
        ]
      },
      "Id": "cdf7839f-fe4b-444b-8651-dcf78d6b22e4",
      "Page": 1,
      "SearchKey": "NEW"
    },
    {
      "BlockType": "WORD",
      "Confidence": 99.37725830078125,
      "Text": "AND",
      "TextType": "PRINTED",
      "Geometry": {
        "BoundingBox": {
          "Width": 0.03424328193068504,
          "Height": 0.015654072165489197,
          "Left": 0.41830241680145264,
          "Top": 0.26404905319213867
        },
        "Polygon": [
          {
            "X": 0.41835567355155945,
            "Y": 0.26404905319213867
          },
          {
            "X": 0.452545702457428,
            "Y": 0.26412075757980347
          },
          {
            "X": 0.4524917006492615,
            "Y": 0.27970314025878906
          },
          {
            "X": 0.41830241680145264,
            "Y": 0.27962395548820496
          }
        ]
      },
      "Id": "76551f6e-4457-4ed3-9bac-9299d9cadc7d",
      "Page": 1,
      "SearchKey": "AND"
    },
    {
      "BlockType": "WORD",
      "Confidence": 99.85271453857422,
      "Text": "CHOICE",
      "TextType": "PRINTED",
      "Geometry": {
        "BoundingBox": {
          "Width": 0.05682724341750145,
          "Height": 0.015816705301404,
          "Left": 0.4617345333099365,
          "Top": 0.2638322412967682
        },
        "Polygon": [
          {
            "X": 0.4617891013622284,
            "Y": 0.2638322412967682
          },
          {
            "X": 0.5185617804527283,
            "Y": 0.26395103335380554
          },
          {
            "X": 0.518505871295929,
            "Y": 0.27964892983436584
          },
          {
            "X": 0.4617345333099365,
            "Y": 0.27951762080192566
          }
        ]
      },
      "Id": "f265bdd7-6424-4529-a300-fef7e726df72",
      "Page": 1,
      "SearchKey": "CHOICE"
    },
    {
      "BlockType": "WORD",
      "Confidence": 99.91600799560547,
      "Text": "COLLECTION",
      "TextType": "PRINTED",
      "Geometry": {
        "BoundingBox": {
          "Width": 0.09626857191324234,
          "Height": 0.015627361834049225,
          "Left": 0.5272541046142578,
          "Top": 0.2643245756626129
        },
        "Polygon": [
          {
            "X": 0.5273091197013855,
            "Y": 0.2643245756626129
          },
          {
            "X": 0.6235226988792419,
            "Y": 0.2645263671875
          },
          {
            "X": 0.6234655380249023,
            "Y": 0.27995193004608154
          },
          {
            "X": 0.5272541046142578,
            "Y": 0.27972930669784546
          }
        ]
      },
      "Id": "18820092-db37-444a-a62b-df3abf2acede",
      "Page": 1,
      "SearchKey": "COLLECTION"
    },
    {
      "BlockType": "WORD",
      "Confidence": 99.87769317626953,
      "Text": "OF",
      "TextType": "PRINTED",
      "Geometry": {
        "BoundingBox": {
          "Width": 0.019346922636032104,
          "Height": 0.014905952848494053,
          "Left": 0.6333962678909302,
          "Top": 0.2644574046134949
        },
        "Polygon": [
          {
            "X": 0.633451521396637,
            "Y": 0.2644574046134949
          },
          {
            "X": 0.6527431607246399,
            "Y": 0.264497846364975
          },
          {
            "X": 0.6526874303817749,
            "Y": 0.27936336398124695
          },
          {
            "X": 0.6333962678909302,
            "Y": 0.2793188989162445
          }
        ]
      },
      "Id": "780d691f-6591-41d3-82f2-78293b25d540",
      "Page": 1,
      "SearchKey": "OF"
    },
    {
      "BlockType": "WORD",
      "Confidence": 99.8932113647461,
      "Text": "HYMNS",
      "TextType": "PRINTED",
      "Geometry": {
        "BoundingBox": {
          "Width": 0.2066108137369156,
          "Height": 0.04216732829809189,
          "Left": 0.2114965319633484,
          "Top": 0.32432353496551514
        },
        "Polygon": [
          {
            "X": 0.2116261124610901,
            "Y": 0.32432353496551514
          },
          {
            "X": 0.4181073307991028,
            "Y": 0.3249335289001465
          },
          {
            "X": 0.417965292930603,
            "Y": 0.3664908707141876
          },
          {
            "X": 0.2114965319633484,
            "Y": 0.36576005816459656
          }
        ]
      },
      "Id": "7ded03dd-f0d3-48ce-ad14-b34e6ffdb5eb",
      "Page": 1,
      "SearchKey": "HYMNS"
    },
    {
      "BlockType": "WORD",
      "Confidence": 99.61932373046875,
      "Text": "AND",
      "TextType": "PRINTED",
      "Geometry": {
        "BoundingBox": {
          "Width": 0.1228073462843895,
          "Height": 0.040088918060064316,
          "Left": 0.44004595279693604,
          "Top": 0.32523953914642334
        },
        "Polygon": [
          {
            "X": 0.44018271565437317,
            "Y": 0.32523953914642334
          },
          {
            "X": 0.5628532767295837,
            "Y": 0.32560235261917114
          },
          {
            "X": 0.562709391117096,
            "Y": 0.36532843112945557
          },
          {
            "X": 0.44004595279693604,
            "Y": 0.3648971617221832
          }
        ]
      },
      "Id": "1a9ec00a-a7a3-463a-8745-e2d14fd4d1df",
      "Page": 1,
      "SearchKey": "AND"
    },
    {
      "BlockType": "WORD",
      "Confidence": 99.03802490234375,
      "Text": "TUNES,",
      "TextType": "PRINTED",
      "Geometry": {
        "BoundingBox": {
          "Width": 0.2078767716884613,
          "Height": 0.05000729113817215,
          "Left": 0.5892186760902405,
          "Top": 0.3242526650428772
        },
        "Polygon": [
          {
            "X": 0.5893989205360413,
            "Y": 0.3242526650428772
          },
          {
            "X": 0.7970954179763794,
            "Y": 0.3248627781867981
          },
          {
            "X": 0.7969002723693848,
            "Y": 0.37425994873046875
          },
          {
            "X": 0.5892186760902405,
            "Y": 0.3735061585903168
          }
        ]
      },
      "Id": "04aa1a39-ec42-42f4-a2b0-c58120c5c48c",
      "Page": 1,
      "SearchKey": "TUNES,"
    },
    {
      "BlockType": "WORD",
      "Confidence": 99.90203094482422,
      "Text": "ORIGINAL",
      "TextType": "PRINTED",
      "Geometry": {
        "BoundingBox": {
          "Width": 0.07546614110469818,
          "Height": 0.015478386543691158,
          "Left": 0.3791244626045227,
          "Top": 0.41258504986763
        },
        "Polygon": [
          {
            "X": 0.3791753947734833,
            "Y": 0.41258504986763
          },
          {
            "X": 0.4545906186103821,
            "Y": 0.4129011034965515
          },
          {
            "X": 0.4545379877090454,
            "Y": 0.42806342244148254
          },
          {
            "X": 0.3791244626045227,
            "Y": 0.4277312755584717
          }
        ]
      },
      "Id": "f29a6829-76a6-40d4-b560-b63e15072318",
      "Page": 1,
      "SearchKey": "ORIGINAL"
    },
    {
      "BlockType": "WORD",
      "Confidence": 99.44142150878906,
      "Text": "AND",
      "TextType": "PRINTED",
      "Geometry": {
        "BoundingBox": {
          "Width": 0.03395753353834152,
          "Height": 0.015025773085653782,
          "Left": 0.46309855580329895,
          "Top": 0.4128634035587311
        },
        "Polygon": [
          {
            "X": 0.46315035223960876,
            "Y": 0.4128634035587311
          },
          {
            "X": 0.49705609679222107,
            "Y": 0.4130054712295532
          },
          {
            "X": 0.49700355529785156,
            "Y": 0.4278891682624817
          },
          {
            "X": 0.46309855580329895,
            "Y": 0.4277400076389313
          }
        ]
      },
      "Id": "c7aaa7de-ab50-4ee8-8373-7f6906b0a6f7",
      "Page": 1,
      "SearchKey": "AND"
    },
    {
      "BlockType": "WORD",
      "Confidence": 99.7782974243164,
      "Text": "SELECTED,",
      "TextType": "PRINTED",
      "Geometry": {
        "BoundingBox": {
          "Width": 0.08276741951704025,
          "Height": 0.01932413876056671,
          "Left": 0.5065785050392151,
          "Top": 0.4131428599357605
        },
        "Polygon": [
          {
            "X": 0.506645679473877,
            "Y": 0.4131428599357605
          },
          {
            "X": 0.5893459320068359,
            "Y": 0.4134894907474518
          },
          {
            "X": 0.5892764925956726,
            "Y": 0.4324670135974884
          },
          {
            "X": 0.5065785050392151,
            "Y": 0.4320983290672302
          }
        ]
      },
      "Id": "e761e6e7-bbfb-4274-91b3-6ab86ea36ac5",
      "Page": 1,
      "SearchKey": "SELECTED,"
    },
    {
      "BlockType": "WORD",
      "Confidence": 99.20659637451172,
      "Text": "FOR",
      "TextType": "PRINTED",
      "Geometry": {
        "BoundingBox": {
          "Width": 0.03030209243297577,
          "Height": 0.014835448935627937,
          "Left": 0.598389744758606,
          "Top": 0.4133358597755432
        },
        "Polygon": [
          {
            "X": 0.5984436869621277,
            "Y": 0.4133358597755432
          },
          {
            "X": 0.6286917924880981,
            "Y": 0.4134625792503357
          },
          {
            "X": 0.6286371946334839,
            "Y": 0.4281713366508484
          },
          {
            "X": 0.598389744758606,
            "Y": 0.4280383884906769
          }
        ]
      },
      "Id": "d9d57756-83f5-4e99-bfd3-ed9bbea082bc",
      "Page": 1,
      "SearchKey": "FOR"
    },
    {
      "BlockType": "WORD",
      "Confidence": 99.81375885009766,
      "Text": "SABBATH",
      "TextType": "PRINTED",
      "Geometry": {
        "BoundingBox": {
          "Width": 0.14017353951931,
          "Height": 0.027587804943323135,
          "Left": 0.187910795211792,
          "Top": 0.47254830598831177
        },
        "Polygon": [
          {
            "X": 0.18799380958080292,
            "Y": 0.47254830598831177
          },
          {
            "X": 0.3280843198299408,
            "Y": 0.4732557237148285
          },
          {
            "X": 0.32799583673477173,
            "Y": 0.500136137008667
          },
          {
            "X": 0.187910795211792,
            "Y": 0.4993756115436554
          }
        ]
      },
      "Id": "dc1c323d-cf4f-4eb8-9ae6-b0641e1adb4b",
      "Page": 1,
      "SearchKey": "SABBATH"
    },
    {
      "BlockType": "WORD",
      "Confidence": 99.92144775390625,
      "Text": "SCHOOLS",
      "TextType": "PRINTED",
      "Geometry": {
        "BoundingBox": {
          "Width": 0.12821343541145325,
          "Height": 0.027735935524106026,
          "Left": 0.3356649875640869,
          "Top": 0.4723641276359558
        },
        "Polygon": [
          {
            "X": 0.33575430512428284,
            "Y": 0.4723641276359558
          },
          {
            "X": 0.46387842297554016,
            "Y": 0.4730094373226166
          },
          {
            "X": 0.4637840688228607,
            "Y": 0.5001000761985779
          },
          {
            "X": 0.3356649875640869,
            "Y": 0.4994059205055237
          }
        ]
      },
      "Id": "08538ef6-cc02-4a96-9ad6-3219053afc4f",
      "Page": 1,
      "SearchKey": "SCHOOLS"
    },
    {
      "BlockType": "WORD",
      "Confidence": 98.45043182373047,
      "Text": "AND",
      "TextType": "PRINTED",
      "Geometry": {
        "BoundingBox": {
          "Width": 0.0640268623828888,
          "Height": 0.026035768911242485,
          "Left": 0.4736930727958679,
          "Top": 0.47280240058898926
        },
        "Polygon": [
          {
            "X": 0.47378289699554443,
            "Y": 0.47280240058898926
          },
          {
            "X": 0.5377199053764343,
            "Y": 0.4731242060661316
          },
          {
            "X": 0.5376276969909668,
            "Y": 0.4988381564617157
          },
          {
            "X": 0.4736930727958679,
            "Y": 0.4984932541847229
          }
        ]
      },
      "Id": "90363309-914e-42b1-850a-be9e83c959cd",
      "Page": 1,
      "SearchKey": "AND"
    },
    {
      "BlockType": "WORD",
      "Confidence": 99.37228393554688,
      "Text": "THE",
      "TextType": "PRINTED",
      "Geometry": {
        "BoundingBox": {
          "Width": 0.06043858453631401,
          "Height": 0.025626156479120255,
          "Left": 0.5463635921478271,
          "Top": 0.47343868017196655
        },
        "Polygon": [
          {
            "X": 0.546454668045044,
            "Y": 0.47343868017196655
          },
          {
            "X": 0.6068021655082703,
            "Y": 0.47374263405799866
          },
          {
            "X": 0.6067088842391968,
            "Y": 0.4990648329257965
          },
          {
            "X": 0.5463635921478271,
            "Y": 0.49873942136764526
          }
        ]
      },
      "Id": "7b6edcf0-20a1-4d12-b44c-602d56c1eb39",
      "Page": 1,
      "SearchKey": "THE"
    },
    {
      "BlockType": "WORD",
      "Confidence": 99.90198516845703,
      "Text": "HOME",
      "TextType": "PRINTED",
      "Geometry": {
        "BoundingBox": {
          "Width": 0.08513257652521133,
          "Height": 0.026735754683613777,
          "Left": 0.6156060099601746,
          "Top": 0.472840815782547
        },
        "Polygon": [
          {
            "X": 0.6157031655311584,
            "Y": 0.472840815782547
          },
          {
            "X": 0.7007385492324829,
            "Y": 0.4732680022716522
          },
          {
            "X": 0.7006381750106812,
            "Y": 0.499576598405838
          },
          {
            "X": 0.6156060099601746,
            "Y": 0.49911803007125854
          }
        ]
      },
      "Id": "55c75503-34c8-48a2-8260-41981331730b",
      "Page": 1,
      "SearchKey": "HOME"
    },
    {
      "BlockType": "WORD",
      "Confidence": 98.70614624023438,
      "Text": "CIRCLE.",
      "TextType": "PRINTED",
      "Geometry": {
        "BoundingBox": {
          "Width": 0.10912667214870453,
          "Height": 0.028014281764626503,
          "Left": 0.7107272744178772,
          "Top": 0.47293686866760254
        },
        "Polygon": [
          {
            "X": 0.7108322978019714,
            "Y": 0.47293686866760254
          },
          {
            "X": 0.8198539018630981,
            "Y": 0.47348397970199585
          },
          {
            "X": 0.8197444677352905,
            "Y": 0.5009511709213257
          },
          {
            "X": 0.7107272744178772,
            "Y": 0.5003621578216553
          }
        ]
      },
      "Id": "dad1c89a-f25c-4148-af95-ef43bc29fe7e",
      "Page": 1,
      "SearchKey": "CIRCLE."
    },
    {
      "BlockType": "WORD",
      "Confidence": 99.9520034790039,
      "Text": "By",
      "TextType": "PRINTED",
      "Geometry": {
        "BoundingBox": {
          "Width": 0.03280260041356087,
          "Height": 0.028081566095352173,
          "Left": 0.3859429657459259,
          "Top": 0.5469735264778137
        },
        "Polygon": [
          {
            "X": 0.3860369920730591,
            "Y": 0.5469735264778137
          },
          {
            "X": 0.4187455475330353,
            "Y": 0.5471725463867188
          },
          {
            "X": 0.41865020990371704,
            "Y": 0.5750550627708435
          },
          {
            "X": 0.3859429657459259,
            "Y": 0.5748432278633118
          }
        ]
      },
      "Id": "ff798630-4662-44c0-8d07-440fd9dee5ce",
      "Page": 1,
      "SearchKey": "By"
    },
    {
      "BlockType": "WORD",
      "Confidence": 99.4423828125,
      "Text": "H.",
      "TextType": "PRINTED",
      "Geometry": {
        "BoundingBox": {
          "Width": 0.02693081833422184,
          "Height": 0.02397342398762703,
          "Left": 0.42583000659942627,
          "Top": 0.5468144416809082
        },
        "Polygon": [
          {
            "X": 0.42591163516044617,
            "Y": 0.5468144416809082
          },
          {
            "X": 0.45276081562042236,
            "Y": 0.5469776391983032
          },
          {
            "X": 0.45267826318740845,
            "Y": 0.5707879066467285
          },
          {
            "X": 0.42583000659942627,
            "Y": 0.5706156492233276
          }
        ]
      },
      "Id": "f768cdf0-52b5-49df-b707-596bb4002ed3",
      "Page": 1,
      "SearchKey": "H."
    },
    {
      "BlockType": "WORD",
      "Confidence": 98.4735107421875,
      "Text": "T.",
      "TextType": "PRINTED",
      "Geometry": {
        "BoundingBox": {
          "Width": 0.022100957110524178,
          "Height": 0.022996563464403152,
          "Left": 0.46231913566589355,
          "Top": 0.5474351048469543
        },
        "Polygon": [
          {
            "X": 0.4623987078666687,
            "Y": 0.5474351048469543
          },
          {
            "X": 0.4844200909137726,
            "Y": 0.5475690960884094
          },
          {
            "X": 0.48433980345726013,
            "Y": 0.5704317092895508
          },
          {
            "X": 0.46231913566589355,
            "Y": 0.5702906250953674
          }
        ]
      },
      "Id": "fe647522-6732-432a-8931-a4bea9e568c3",
      "Page": 1,
      "SearchKey": "T."
    },
    {
      "BlockType": "WORD",
      "Confidence": 98.61727905273438,
      "Text": "MERRILL.",
      "TextType": "PRINTED",
      "Geometry": {
        "BoundingBox": {
          "Width": 0.12267813831567764,
          "Height": 0.02483608014881611,
          "Left": 0.493821382522583,
          "Top": 0.546153724193573
        },
        "Polygon": [
          {
            "X": 0.493906170129776,
            "Y": 0.546153724193573
          },
          {
            "X": 0.6164995431900024,
            "Y": 0.5468970537185669
          },
          {
            "X": 0.6164104342460632,
            "Y": 0.5709897875785828
          },
          {
            "X": 0.493821382522583,
            "Y": 0.5702049732208252
          }
        ]
      },
      "Id": "516eaee0-e3ca-454f-95fd-5ebbf08353e6",
      "Page": 1,
      "SearchKey": "MERRILL."
    },
    {
      "BlockType": "WORD",
      "Confidence": 84.0847396850586,
      "Text": "\"O",
      "TextType": "PRINTED",
      "Geometry": {
        "BoundingBox": {
          "Width": 0.021091831848025322,
          "Height": 0.015570152550935745,
          "Left": 0.33758947253227234,
          "Top": 0.6540601253509521
        },
        "Polygon": [
          {
            "X": 0.3376404047012329,
            "Y": 0.6540601253509521
          },
          {
            "X": 0.3586812913417816,
            "Y": 0.6542199850082397
          },
          {
            "X": 0.35862988233566284,
            "Y": 0.669630229473114
          },
          {
            "X": 0.33758947253227234,
            "Y": 0.6694658398628235
          }
        ]
      },
      "Id": "62427248-471c-4d1f-b10d-33acd56af15a",
      "Page": 1,
      "SearchKey": "\"O"
    },
    {
      "BlockType": "WORD",
      "Confidence": 99.94087219238281,
      "Text": "sing",
      "TextType": "PRINTED",
      "Geometry": {
        "BoundingBox": {
          "Width": 0.03140991926193237,
          "Height": 0.017764611169695854,
          "Left": 0.36311790347099304,
          "Top": 0.6546372771263123
        },
        "Polygon": [
          {
            "X": 0.3631764352321625,
            "Y": 0.6546372771263123
          },
          {
            "X": 0.3945278227329254,
            "Y": 0.654875636100769
          },
          {
            "X": 0.3944684565067291,
            "Y": 0.6724018454551697
          },
          {
            "X": 0.36311790347099304,
            "Y": 0.6721557378768921
          }
        ]
      },
      "Id": "e7744a51-aeef-4200-8fd9-d518415f03e4",
      "Page": 1,
      "SearchKey": "sing"
    },
    {
      "BlockType": "WORD",
      "Confidence": 99.67070007324219,
      "Text": "unto",
      "TextType": "PRINTED",
      "Geometry": {
        "BoundingBox": {
          "Width": 0.03230762481689453,
          "Height": 0.01391929667443037,
          "Left": 0.3993752598762512,
          "Top": 0.6552861332893372
        },
        "Polygon": [
          {
            "X": 0.3994216322898865,
            "Y": 0.6552861332893372
          },
          {
            "X": 0.43168288469314575,
            "Y": 0.655531644821167
          },
          {
            "X": 0.43163585662841797,
            "Y": 0.6692054271697998
          },
          {
            "X": 0.3993752598762512,
            "Y": 0.6689537167549133
          }
        ]
      },
      "Id": "026be9a9-0bde-45ec-90f9-746c8852e18f",
      "Page": 1,
      "SearchKey": "unto"
    },
    {
      "BlockType": "WORD",
      "Confidence": 99.9702377319336,
      "Text": "the",
      "TextType": "PRINTED",
      "Geometry": {
        "BoundingBox": {
          "Width": 0.022329872474074364,
          "Height": 0.014384996145963669,
          "Left": 0.4362487494945526,
          "Top": 0.654243528842926
        },
        "Polygon": [
          {
            "X": 0.4362977147102356,
            "Y": 0.654243528842926
          },
          {
            "X": 0.45857861638069153,
            "Y": 0.6544126868247986
          },
          {
            "X": 0.45852920413017273,
            "Y": 0.6686285138130188
          },
          {
            "X": 0.4362487494945526,
            "Y": 0.6684549450874329
          }
        ]
      },
      "Id": "30f3e2cb-b819-4086-a224-f25819ee43f6",
      "Page": 1,
      "SearchKey": "the"
    },
    {
      "BlockType": "WORD",
      "Confidence": 99.83525848388672,
      "Text": "Lord",
      "TextType": "PRINTED",
      "Geometry": {
        "BoundingBox": {
          "Width": 0.03626592457294464,
          "Height": 0.015132557600736618,
          "Left": 0.46293485164642334,
          "Top": 0.6537294983863831
        },
        "Polygon": [
          {
            "X": 0.4629865884780884,
            "Y": 0.6537294983863831
          },
          {
            "X": 0.4992007911205292,
            "Y": 0.6540040373802185
          },
          {
            "X": 0.49914827942848206,
            "Y": 0.6688621044158936
          },
          {
            "X": 0.46293485164642334,
            "Y": 0.6685799956321716
          }
        ]
      },
      "Id": "3abf5faa-29e7-4aea-9f88-4a60f3598558",
      "Page": 1,
      "SearchKey": "Lord"
    },
    {
      "BlockType": "WORD",
      "Confidence": 99.83033752441406,
      "Text": "a",
      "TextType": "PRINTED",
      "Geometry": {
        "BoundingBox": {
          "Width": 0.010075092315673828,
          "Height": 0.010460585355758667,
          "Left": 0.5040256381034851,
          "Top": 0.6577740907669067
        },
        "Polygon": [
          {
            "X": 0.5040624141693115,
            "Y": 0.6577740907669067
          },
          {
            "X": 0.5141007304191589,
            "Y": 0.6578507423400879
          },
          {
            "X": 0.514063835144043,
            "Y": 0.6682347059249878
          },
          {
            "X": 0.5040256381034851,
            "Y": 0.668156623840332
          }
        ]
      },
      "Id": "84272ffb-f535-4776-ab1c-e41d593c8d30",
      "Page": 1,
      "SearchKey": "a"
    },
    {
      "BlockType": "WORD",
      "Confidence": 99.92134857177734,
      "Text": "new",
      "TextType": "PRINTED",
      "Geometry": {
        "BoundingBox": {
          "Width": 0.029439669102430344,
          "Height": 0.011330746114253998,
          "Left": 0.5184576511383057,
          "Top": 0.6578166484832764
        },
        "Polygon": [
          {
            "X": 0.5184972286224365,
            "Y": 0.6578166484832764
          },
          {
            "X": 0.5478973388671875,
            "Y": 0.6580410599708557
          },
          {
            "X": 0.5478573441505432,
            "Y": 0.6691473722457886
          },
          {
            "X": 0.5184576511383057,
            "Y": 0.6689184308052063
          }
        ]
      },
      "Id": "588b5aa8-e595-40ea-b3d0-1060a024750e",
      "Page": 1,
      "SearchKey": "new"
    },
    {
      "BlockType": "WORD",
      "Confidence": 95.06488037109375,
      "Text": "song.\"-Ps.",
      "TextType": "PRINTED",
      "Geometry": {
        "BoundingBox": {
          "Width": 0.07584483176469803,
          "Height": 0.018161585554480553,
          "Left": 0.5526776313781738,
          "Top": 0.6542412638664246
        },
        "Polygon": [
          {
            "X": 0.5527410507202148,
            "Y": 0.6542412638664246
          },
          {
            "X": 0.628522515296936,
            "Y": 0.6548154950141907
          },
          {
            "X": 0.6284571290016174,
            "Y": 0.6724027991294861
          },
          {
            "X": 0.5526776313781738,
            "Y": 0.6718098521232605
          }
        ]
      },
      "Id": "3199faa9-92f3-4206-97a2-a44b75af649d",
      "Page": 1,
      "SearchKey": "song.\"-Ps."
    },
    {
      "BlockType": "WORD",
      "Confidence": 99.67363739013672,
      "Text": "96:",
      "TextType": "PRINTED",
      "Geometry": {
        "BoundingBox": {
          "Width": 0.01835545524954796,
          "Height": 0.014564377255737782,
          "Left": 0.6318396329879761,
          "Top": 0.6549710035324097
        },
        "Polygon": [
          {
            "X": 0.6318933367729187,
            "Y": 0.6549710035324097
          },
          {
            "X": 0.6501951217651367,
            "Y": 0.655109703540802
          },
          {
            "X": 0.6501410603523254,
            "Y": 0.6695353984832764
          },
          {
            "X": 0.6318396329879761,
            "Y": 0.6693929433822632
          }
        ]
      },
      "Id": "b246cc30-097a-4b84-8150-d56281637ff7",
      "Page": 1,
      "SearchKey": "96:"
    },
    {
      "BlockType": "WORD",
      "Confidence": 98.08765411376953,
      "Text": "1.",
      "TextType": "PRINTED",
      "Geometry": {
        "BoundingBox": {
          "Width": 0.011278299614787102,
          "Height": 0.01576242409646511,
          "Left": 0.6547876596450806,
          "Top": 0.6542046070098877
        },
        "Polygon": [
          {
            "X": 0.6548464894294739,
            "Y": 0.6542046070098877
          },
          {
            "X": 0.6660659313201904,
            "Y": 0.6542894840240479
          },
          {
            "X": 0.666006863117218,
            "Y": 0.669966995716095
          },
          {
            "X": 0.6547876596450806,
            "Y": 0.669879674911499
          }
        ]
      },
      "Id": "09034c13-4ae6-49da-a838-74311901cd91",
      "Page": 1,
      "SearchKey": "1."
    },
    {
      "BlockType": "WORD",
      "Confidence": 95.89713287353516,
      "Text": "CINCINNATI:",
      "TextType": "PRINTED",
      "Geometry": {
        "BoundingBox": {
          "Width": 0.1974916160106659,
          "Height": 0.026002755388617516,
          "Left": 0.4030933380126953,
          "Top": 0.7531004548072815
        },
        "Polygon": [
          {
            "X": 0.4031754732131958,
            "Y": 0.7531004548072815
          },
          {
            "X": 0.6005849242210388,
            "Y": 0.7548745274543762
          },
          {
            "X": 0.6004958748817444,
            "Y": 0.7791032195091248
          },
          {
            "X": 0.4030933380126953,
            "Y": 0.7772620320320129
          }
        ]
      },
      "Id": "7621164c-1f39-4993-b463-7c434e08885b",
      "Page": 1,
      "SearchKey": "CINCINNATI:"
    },
    {
      "BlockType": "WORD",
      "Confidence": 52.65187072753906,
      "Text": "PU-BLISHED",
      "TextType": "PRINTED",
      "Geometry": {
        "BoundingBox": {
          "Width": 0.1630263328552246,
          "Height": 0.019980335608124733,
          "Left": 0.24174480140209198,
          "Top": 0.7855256199836731
        },
        "Polygon": [
          {
            "X": 0.2418031543493271,
            "Y": 0.7855256199836731
          },
          {
            "X": 0.4047711491584778,
            "Y": 0.7870681285858154
          },
          {
            "X": 0.4047084152698517,
            "Y": 0.8055059909820557
          },
          {
            "X": 0.24174480140209198,
            "Y": 0.8039211630821228
          }
        ]
      },
      "Id": "29bbbfec-6bf3-4842-952d-567cc51c1fba",
      "Page": 1,
      "SearchKey": "PU-BLISHED"
    },
    {
      "BlockType": "WORD",
      "Confidence": 99.83941650390625,
      "Text": "BY",
      "TextType": "PRINTED",
      "Geometry": {
        "BoundingBox": {
          "Width": 0.03884187713265419,
          "Height": 0.01726914756000042,
          "Left": 0.4168301224708557,
          "Top": 0.7871069312095642
        },
        "Polygon": [
          {
            "X": 0.4168878495693207,
            "Y": 0.7871069312095642
          },
          {
            "X": 0.4556719958782196,
            "Y": 0.7874739766120911
          },
          {
            "X": 0.45561328530311584,
            "Y": 0.8043760657310486
          },
          {
            "X": 0.4168301224708557,
            "Y": 0.8039997816085815
          }
        ]
      },
      "Id": "23ee0642-cd88-40ff-b11d-0ac5aed697ca",
      "Page": 1,
      "SearchKey": "BY"
    },
    {
      "BlockType": "WORD",
      "Confidence": 99.97134399414062,
      "Text": "JOHN",
      "TextType": "PRINTED",
      "Geometry": {
        "BoundingBox": {
          "Width": 0.07420308887958527,
          "Height": 0.017338832840323448,
          "Left": 0.4670429825782776,
          "Top": 0.7878068089485168
        },
        "Polygon": [
          {
            "X": 0.46710097789764404,
            "Y": 0.7878068089485168
          },
          {
            "X": 0.5412460565567017,
            "Y": 0.7885087728500366
          },
          {
            "X": 0.5411862730979919,
            "Y": 0.8051456212997437
          },
          {
            "X": 0.4670429825782776,
            "Y": 0.804426372051239
          }
        ]
      },
      "Id": "5b8f95d6-bb20-4a49-af69-81b1b66d650e",
      "Page": 1,
      "SearchKey": "JOHN"
    },
    {
      "BlockType": "WORD",
      "Confidence": 99.83121490478516,
      "Text": "CHURCH",
      "TextType": "PRINTED",
      "Geometry": {
        "BoundingBox": {
          "Width": 0.11425013840198517,
          "Height": 0.01902499608695507,
          "Left": 0.5531094074249268,
          "Top": 0.7871828079223633
        },
        "Polygon": [
          {
            "X": 0.5531740784645081,
            "Y": 0.7871828079223633
          },
          {
            "X": 0.6673595309257507,
            "Y": 0.7882614731788635
          },
          {
            "X": 0.6672918796539307,
            "Y": 0.8062077760696411
          },
          {
            "X": 0.5531094074249268,
            "Y": 0.8051003217697144
          }
        ]
      },
      "Id": "6a0549f0-03c4-4cb4-bf05-714d7fe1bce7",
      "Page": 1,
      "SearchKey": "CHURCH"
    },
    {
      "BlockType": "WORD",
      "Confidence": 99.96013641357422,
      "Text": "&",
      "TextType": "PRINTED",
      "Geometry": {
        "BoundingBox": {
          "Width": 0.020267397165298462,
          "Height": 0.017436467111110687,
          "Left": 0.6785301566123962,
          "Top": 0.7887976169586182
        },
        "Polygon": [
          {
            "X": 0.6785954833030701,
            "Y": 0.7887976169586182
          },
          {
            "X": 0.6987975835800171,
            "Y": 0.7889885902404785
          },
          {
            "X": 0.6987317800521851,
            "Y": 0.8062340617179871
          },
          {
            "X": 0.6785301566123962,
            "Y": 0.8060382008552551
          }
        ]
      },
      "Id": "9f86b129-1531-44c5-a34a-508e628ad9ad",
      "Page": 1,
      "SearchKey": "&"
    },
    {
      "BlockType": "WORD",
      "Confidence": 95.53461456298828,
      "Text": "CO.,",
      "TextType": "PRINTED",
      "Geometry": {
        "BoundingBox": {
          "Width": 0.04723599553108215,
          "Height": 0.02067573182284832,
          "Left": 0.7109606862068176,
          "Top": 0.788206934928894
        },
        "Polygon": [
          {
            "X": 0.7110381722450256,
            "Y": 0.788206934928894
          },
          {
            "X": 0.7581966519355774,
            "Y": 0.7886521220207214
          },
          {
            "X": 0.7581177949905396,
            "Y": 0.8088826537132263
          },
          {
            "X": 0.7109606862068176,
            "Y": 0.8084241151809692
          }
        ]
      },
      "Id": "29fed303-6a93-4e22-932c-f01d5abc9f80",
      "Page": 1,
      "SearchKey": "CO.,"
    },
    {
      "BlockType": "WORD",
      "Confidence": 99.88211822509766,
      "Text": "66",
      "TextType": "PRINTED",
      "Geometry": {
        "BoundingBox": {
          "Width": 0.01995994709432125,
          "Height": 0.016979120671749115,
          "Left": 0.3701103627681732,
          "Top": 0.8164577484130859
        },
        "Polygon": [
          {
            "X": 0.3701665997505188,
            "Y": 0.8164577484130859
          },
          {
            "X": 0.3900703191757202,
            "Y": 0.8166544437408447
          },
          {
            "X": 0.39001357555389404,
            "Y": 0.8334368467330933
          },
          {
            "X": 0.3701103627681732,
            "Y": 0.8332354426383972
          }
        ]
      },
      "Id": "306b0b47-1f0f-418b-9ebc-4644740af7b4",
      "Page": 1,
      "SearchKey": "66"
    },
    {
      "BlockType": "WORD",
      "Confidence": 99.67740631103516,
      "Text": "WEST",
      "TextType": "PRINTED",
      "Geometry": {
        "BoundingBox": {
          "Width": 0.056173838675022125,
          "Height": 0.01789144240319729,
          "Left": 0.3956228494644165,
          "Top": 0.816287636756897
        },
        "Polygon": [
          {
            "X": 0.3956815302371979,
            "Y": 0.816287636756897
          },
          {
            "X": 0.45179668068885803,
            "Y": 0.8168419003486633
          },
          {
            "X": 0.45173656940460205,
            "Y": 0.8341790437698364
          },
          {
            "X": 0.3956228494644165,
            "Y": 0.8336110711097717
          }
        ]
      },
      "Id": "8a1f61b9-f997-439d-bd90-f7c03455f0ab",
      "Page": 1,
      "SearchKey": "WEST"
    },
    {
      "BlockType": "WORD",
      "Confidence": 99.91620635986328,
      "Text": "FOURTH",
      "TextType": "PRINTED",
      "Geometry": {
        "BoundingBox": {
          "Width": 0.08103513717651367,
          "Height": 0.018147023394703865,
          "Left": 0.45809000730514526,
          "Top": 0.816936731338501
        },
        "Polygon": [
          {
            "X": 0.4581502676010132,
            "Y": 0.816936731338501
          },
          {
            "X": 0.5391251444816589,
            "Y": 0.8177366256713867
          },
          {
            "X": 0.5390628576278687,
            "Y": 0.8350837826728821
          },
          {
            "X": 0.45809000730514526,
            "Y": 0.8342641592025757
          }
        ]
      },
      "Id": "ae2c7d9a-10de-4b24-8906-4b5880906e8c",
      "Page": 1,
      "SearchKey": "FOURTH"
    },
    {
      "BlockType": "WORD",
      "Confidence": 95.9316635131836,
      "Text": "STREET.",
      "TextType": "PRINTED",
      "Geometry": {
        "BoundingBox": {
          "Width": 0.07958312332630157,
          "Height": 0.020297067239880562,
          "Left": 0.5473014116287231,
          "Top": 0.8178627490997314
        },
        "Polygon": [
          {
            "X": 0.5473716259002686,
            "Y": 0.8178627490997314
          },
          {
            "X": 0.6268845796585083,
            "Y": 0.8186482787132263
          },
          {
            "X": 0.6268121004104614,
            "Y": 0.8381598591804504
          },
          {
            "X": 0.5473014116287231,
            "Y": 0.8373525738716125
          }
        ]
      },
      "Id": "400e09e6-bf34-440d-9412-e398196c8970",
      "Page": 1,
      "SearchKey": "STREET."
    }
  ],
  "AnalyzeDocumentModelVersion": "1.0"
}