<?xml version="1.0" encoding="UTF-8"?>
<pc:PcGts xmlns:pc="http://schema.primaresearch.org/PAGE/gts/pagecontent/2019-07-15" xmlns:xsi="http://www.w3.org/2001/XMLSchema-instance" xsi:schemaLocation="http://schema.primaresearch.org/PAGE/gts/pagecontent/2019-07-15 http://schema.primaresearch.org/PAGE/gts/pagecontent/2019-07-15/pagecontent.xsd">
    <pc:Metadata>
        <pc:Creator>OCR-D/core 2.50.0</pc:Creator>
        <pc:Created>2023-05-03T15:46:33.174446</pc:Created>
        <pc:LastChange>2023-05-03T15:46:33.174446</pc:LastChange>
    </pc:Metadata>
    <pc:Page imageFilename="google-ocr-testbed/images/1874-Palmof-EMU-0065.jpg" imageWidth="2756" imageHeight="2272">
        <pc:TextRegion id="region-b44c6b0f-4f80-4de5-8d0d-d599440b0cb0">
            <pc:Coords points="62,72 2673,83 2699,2204 39,2178"/>
            <pc:TextLine id="line-ab7302fa-6c5f-4ce7-80d0-2004a970cf90">
                <pc:Coords points="2392,260 2453,260 2453,307 2392,307"/>
                <pc:Word id="word-fbc602f2-451b-49a7-9d2c-5e10ae4651c5">
                    <pc:Coords points="2392,260 2453,260 2453,307 2392,307"/>
                    <pc:TextEquiv>
                        <pc:Unicode>61</pc:Unicode>
                    </pc:TextEquiv>
                </pc:Word>
                <pc:TextEquiv>
                    <pc:Unicode>61</pc:Unicode>
                </pc:TextEquiv>
            </pc:TextLine>
            <pc:TextLine id="line-22f739cc-fe3c-45a1-94ad-f46a526280d1">
                <pc:Coords points="526,386 2220,395 2220,482 526,473"/>
                <pc:Word id="word-c9c9de22-a417-4502-94b1-e1d368d1d291">
                    <pc:Coords points="526,394 938,396 938,464 526,462"/>
                    <pc:TextEquiv>
                        <pc:Unicode>Praise</pc:Unicode>
                    </pc:TextEquiv>
                </pc:Word>
                <pc:Word id="word-43b509ff-0923-4870-8a28-62fb43e6d33c">
                    <pc:Coords points="986,396 1209,397 1209,464 986,463"/>
                    <pc:TextEquiv>
                        <pc:Unicode>and</pc:Unicode>
                    </pc:TextEquiv>
                </pc:Word>
                <pc:Word id="word-c3d98b42-b47a-4ec1-bf0f-b172d9fcc9ad">
                    <pc:Coords points="1257,395 1749,397 1749,464 1257,461"/>
                    <pc:TextEquiv>
                        <pc:Unicode>Revival</pc:Unicode>
                    </pc:TextEquiv>
                </pc:Word>
                <pc:Word id="word-2fb0b0bc-3323-4bcf-bab6-1d2ab13d4552">
                    <pc:Coords points="1798,393 2220,395 2220,482 1798,479"/>
                    <pc:TextEquiv>
                        <pc:Unicode>Songs.</pc:Unicode>
                    </pc:TextEquiv>
                </pc:Word>
                <pc:TextEquiv>
                    <pc:Unicode>Praise and Revival Songs.</pc:Unicode>
                </pc:TextEquiv>
            </pc:TextLine>
            <pc:TextLine id="line-4afea64f-0c44-4f5f-b78e-b982e869644e">
                <pc:Coords points="1175,708 1559,710 1560,757 1175,754"/>
                <pc:Word id="word-91c56ea8-9c75-4e44-86bf-505fb62686e3">
                    <pc:Coords points="1175,710 1390,711 1390,756 1175,754"/>
                    <pc:TextEquiv>
                        <pc:Unicode>TARRY</pc:Unicode>
                    </pc:TextEquiv>
                </pc:Word>
                <pc:Word id="word-7aa5b834-417c-462c-837b-b0069ee9d6f2">
                    <pc:Coords points="1420,709 1559,710 1560,756 1420,755"/>
                    <pc:TextEquiv>
                        <pc:Unicode>NOT.</pc:Unicode>
                    </pc:TextEquiv>
                </pc:Word>
                <pc:TextEquiv>
                    <pc:Unicode>TARRY NOT.</pc:Unicode>
                </pc:TextEquiv>
            </pc:TextLine>
            <pc:TextLine id="line-cf1defe9-df6c-4cf4-b206-62982af0c856">
                <pc:Coords points="846,769 1878,775 1878,812 846,806"/>
                <pc:Word id="word-739f836b-4848-4734-b407-6a4f585d9967">
                    <pc:Coords points="846,777 917,778 917,807 846,806"/>
                    <pc:TextEquiv>
                        <pc:Unicode>"He</pc:Unicode>
                    </pc:TextEquiv>
                </pc:Word>
                <pc:Word id="word-e2f8ff8e-2438-45f7-8a48-037e639f2425">
                    <pc:Coords points="926,778 991,779 991,807 926,806"/>
                    <pc:TextEquiv>
                        <pc:Unicode>that</pc:Unicode>
                    </pc:TextEquiv>
                </pc:Word>
                <pc:Word id="word-58bf11ff-8ade-48c5-9e0b-ab5ef583e8b3">
                    <pc:Coords points="1002,777 1117,778 1117,807 1002,806"/>
                    <pc:TextEquiv>
                        <pc:Unicode>cometh</pc:Unicode>
                    </pc:TextEquiv>
                </pc:Word>
                <pc:Word id="word-043bdaaa-9725-4cb6-ac98-f64ebcbee204">
                    <pc:Coords points="1126,782 1157,782 1157,806 1126,806"/>
                    <pc:TextEquiv>
                        <pc:Unicode>to</pc:Unicode>
                    </pc:TextEquiv>
                </pc:Word>
                <pc:Word id="word-291dbc44-061d-45ba-9626-5eddbac61276">
                    <pc:Coords points="1167,785 1214,785 1214,805 1167,805"/>
                    <pc:TextEquiv>
                        <pc:Unicode>me</pc:Unicode>
                    </pc:TextEquiv>
                </pc:Word>
                <pc:Word id="word-555ea5c7-506c-4f73-8d42-28003527bda7">
                    <pc:Coords points="1224,777 1241,777 1241,805 1224,805"/>
                    <pc:TextEquiv>
                        <pc:Unicode>I</pc:Unicode>
                    </pc:TextEquiv>
                </pc:Word>
                <pc:Word id="word-c0bb0dd5-8fdb-45f7-86fc-e076af7fbc21">
                    <pc:Coords points="1252,776 1309,776 1309,804 1252,804"/>
                    <pc:TextEquiv>
                        <pc:Unicode>will</pc:Unicode>
                    </pc:TextEquiv>
                </pc:Word>
                <pc:Word id="word-36ef174b-4200-4d68-b3f1-6d18c402c817">
                    <pc:Coords points="1320,777 1351,777 1351,804 1320,804"/>
                    <pc:TextEquiv>
                        <pc:Unicode>in</pc:Unicode>
                    </pc:TextEquiv>
                </pc:Word>
                <pc:Word id="word-4e249ca1-d3b8-4fae-987e-39cb670b0bff">
                    <pc:Coords points="1361,784 1399,784 1399,804 1361,804"/>
                    <pc:TextEquiv>
                        <pc:Unicode>no</pc:Unicode>
                    </pc:TextEquiv>
                </pc:Word>
                <pc:Word id="word-9f5a923c-2896-4790-9703-78b8cc1d232c">
                    <pc:Coords points="1410,777 1478,777 1478,804 1410,804"/>
                    <pc:TextEquiv>
                        <pc:Unicode>wise</pc:Unicode>
                    </pc:TextEquiv>
                </pc:Word>
                <pc:Word id="word-32a8d78e-7fb7-45b5-97fc-80de48278f0a">
                    <pc:Coords points="1489,780 1551,780 1551,804 1489,804"/>
                    <pc:TextEquiv>
                        <pc:Unicode>cast</pc:Unicode>
                    </pc:TextEquiv>
                </pc:Word>
                <pc:Word id="word-7d7291e3-adec-4b75-a1e7-c6c69975ed19">
                    <pc:Coords points="1560,780 1618,781 1618,804 1560,804"/>
                    <pc:TextEquiv>
                        <pc:Unicode>out.</pc:Unicode>
                    </pc:TextEquiv>
                </pc:Word>
                <pc:Word id="word-e3283004-d91d-4920-800f-68dd72ed3d17">
                    <pc:Coords points="1676,775 1765,775 1765,809 1676,809"/>
                    <pc:TextEquiv>
                        <pc:Unicode>JOHN</pc:Unicode>
                    </pc:TextEquiv>
                </pc:Word>
                <pc:Word id="word-2d639eb0-f7b5-482c-adf8-c04c85ec2f45">
                    <pc:Coords points="1779,775 1821,775 1821,809 1779,809"/>
                    <pc:TextEquiv>
                        <pc:Unicode>vi,</pc:Unicode>
                    </pc:TextEquiv>
                </pc:Word>
                <pc:Word id="word-6138cf9a-070b-4064-bf97-8abaf684bca0">
                    <pc:Coords points="1831,783 1878,783 1878,810 1832,810"/>
                    <pc:TextEquiv>
                        <pc:Unicode>37.</pc:Unicode>
                    </pc:TextEquiv>
                </pc:Word>
                <pc:TextEquiv>
                    <pc:Unicode>"He that cometh to me I will in no wise cast out. JOHN vi, 37.</pc:Unicode>
                </pc:TextEquiv>
            </pc:TextLine>
            <pc:TextLine id="line-abea668f-5fb0-4e46-afd8-9a9b67cb7c16">
                <pc:Coords points="1669,805 2367,809 2367,855 1669,850"/>
                <pc:Word id="word-c91736de-b2e3-4ba4-86a3-770a9d05364d">
                    <pc:Coords points="1669,809 1785,810 1785,843 1669,842"/>
                    <pc:TextEquiv>
                        <pc:Unicode>Words</pc:Unicode>
                    </pc:TextEquiv>
                </pc:Word>
                <pc:Word id="word-bd28696b-3a88-42d4-b5f1-886c532c0fc1">
                    <pc:Coords points="1799,811 1874,811 1875,842 1799,842"/>
                    <pc:TextEquiv>
                        <pc:Unicode>and</pc:Unicode>
                    </pc:TextEquiv>
                </pc:Word>
                <pc:Word id="word-e4a297ec-b7a9-446c-857e-975dee9980fa">
                    <pc:Coords points="1885,808 1999,809 1999,843 1885,843"/>
                    <pc:TextEquiv>
                        <pc:Unicode>Music</pc:Unicode>
                    </pc:TextEquiv>
                </pc:Word>
                <pc:Word id="word-82029411-7b1d-4ceb-a267-cf0a9f308c4c">
                    <pc:Coords points="2012,808 2055,808 2055,853 2012,853"/>
                    <pc:TextEquiv>
                        <pc:Unicode>by</pc:Unicode>
                    </pc:TextEquiv>
                </pc:Word>
                <pc:Word id="word-0e508a6d-b1b2-46bf-b11a-6794f0d074df">
                    <pc:Coords points="2068,807 2112,807 2113,844 2068,843"/>
                    <pc:TextEquiv>
                        <pc:Unicode>L.</pc:Unicode>
                    </pc:TextEquiv>
                </pc:Word>
                <pc:Word id="word-f8de8c87-99bd-4735-b915-dd6f1e78e8da">
                    <pc:Coords points="2129,808 2177,809 2177,844 2129,844"/>
                    <pc:TextEquiv>
                        <pc:Unicode>H.</pc:Unicode>
                    </pc:TextEquiv>
                </pc:Word>
                <pc:Word id="word-5cc0b776-ce16-4938-b893-2d8be85e78e7">
                    <pc:Coords points="2194,809 2367,810 2367,855 2195,854"/>
                    <pc:TextEquiv>
                        <pc:Unicode>Dowling.</pc:Unicode>
                    </pc:TextEquiv>
                </pc:Word>
                <pc:TextEquiv>
                    <pc:Unicode>Words and Music by L. H. Dowling.</pc:Unicode>
                </pc:TextEquiv>
            </pc:TextLine>
            <pc:TextLine id="line-b68adbf2-2e38-4c35-bf46-18fc7846ccb9">
                <pc:Coords points="418,887 446,887 446,928 418,928"/>
                <pc:Word id="word-8b226f83-d98a-468c-a910-62ae6ff99644">
                    <pc:Coords points="418,887 446,887 446,928 418,928"/>
                    <pc:TextEquiv>
                        <pc:Unicode>2</pc:Unicode>
                    </pc:TextEquiv>
                </pc:Word>
                <pc:TextEquiv>
                    <pc:Unicode>2</pc:Unicode>
                </pc:TextEquiv>
            </pc:TextLine>
            <pc:TextLine id="line-292b863e-20d7-4402-95d6-8deb2f8a5e58">
                <pc:Coords points="364,1030 395,1030 395,1056 364,1055"/>
                <pc:Word id="word-0d9545ce-6b19-4e34-a7cf-a5d4013c3613">
                    <pc:Coords points="364,1030 395,1030 395,1056 364,1055"/>
                    <pc:TextEquiv>
                        <pc:Unicode>I.</pc:Unicode>
                    </pc:TextEquiv>
                </pc:Word>
                <pc:TextEquiv>
                    <pc:Unicode>I.</pc:Unicode>
                </pc:TextEquiv>
            </pc:TextLine>
            <pc:TextLine id="line-0ba19bcf-599e-4365-bf8e-e506c92fc119">
                <pc:Coords points="442,1021 548,1022 547,1054 441,1053"/>
                <pc:Word id="word-3efb90f5-3dca-4eab-a5ac-b679ea1a5a78">
                    <pc:Coords points="442,1021 548,1022 547,1054 441,1053"/>
                    <pc:TextEquiv>
                        <pc:Unicode>Come</pc:Unicode>
                    </pc:TextEquiv>
                </pc:Word>
                <pc:TextEquiv>
                    <pc:Unicode>Come</pc:Unicode>
                </pc:TextEquiv>
            </pc:TextLine>
            <pc:TextLine id="line-ea5f03bc-6b0c-485f-8482-519449c95581">
                <pc:Coords points="576,1025 612,1026 612,1052 576,1052"/>
                <pc:Word id="word-c1f7798f-d09a-4138-84e3-e2a961a452b5">
                    <pc:Coords points="576,1025 612,1026 612,1052 576,1052"/>
                    <pc:TextEquiv>
                        <pc:Unicode>to</pc:Unicode>
                    </pc:TextEquiv>
                </pc:Word>
                <pc:TextEquiv>
                    <pc:Unicode>to</pc:Unicode>
                </pc:TextEquiv>
            </pc:TextLine>
            <pc:TextLine id="line-f421f023-5dd4-4b87-9526-b444e8b4557d">
                <pc:Coords points="658,1020 796,1021 796,1062 658,1061"/>
                <pc:Word id="word-21a09536-8a9f-4de9-9097-e48e0f1d8e6a">
                    <pc:Coords points="658,1020 796,1021 796,1062 658,1061"/>
                    <pc:TextEquiv>
                        <pc:Unicode>Je - sus</pc:Unicode>
                    </pc:TextEquiv>
                </pc:Word>
                <pc:TextEquiv>
                    <pc:Unicode>Je - sus</pc:Unicode>
                </pc:TextEquiv>
            </pc:TextLine>
            <pc:TextLine id="line-0bbc11d9-5068-4fa6-b18f-2ed91f8960b5">
                <pc:Coords points="825,1018 916,1019 916,1061 824,1060"/>
                <pc:Word id="word-615d14e0-7272-4282-a3cc-579f26038fde">
                    <pc:Coords points="825,1018 916,1019 916,1061 824,1060"/>
                    <pc:TextEquiv>
                        <pc:Unicode>right</pc:Unicode>
                    </pc:TextEquiv>
                </pc:Word>
                <pc:TextEquiv>
                    <pc:Unicode>right</pc:Unicode>
                </pc:TextEquiv>
            </pc:TextLine>
            <pc:TextLine id="line-afcada3d-75e1-49c8-9ca7-a8ec5964df26">
                <pc:Coords points="996,1025 1103,1026 1103,1058 996,1057"/>
                <pc:Word id="word-799f0ed1-aa7c-42a8-b281-eb56474ae2c4">
                    <pc:Coords points="996,1025 1103,1026 1103,1058 996,1057"/>
                    <pc:TextEquiv>
                        <pc:Unicode>- way,</pc:Unicode>
                    </pc:TextEquiv>
                </pc:Word>
                <pc:TextEquiv>
                    <pc:Unicode>- way,</pc:Unicode>
                </pc:TextEquiv>
            </pc:TextLine>
            <pc:TextLine id="line-a4c46351-e9a8-4d95-9242-0a471e418742">
                <pc:Coords points="1165,1014 1284,1015 1284,1056 1165,1055"/>
                <pc:Word id="word-2f7fe9d2-247e-4c6f-b616-08216f0b2c55">
                    <pc:Coords points="1165,1014 1284,1015 1284,1056 1165,1055"/>
                    <pc:TextEquiv>
                        <pc:Unicode>Tar-ry</pc:Unicode>
                    </pc:TextEquiv>
                </pc:Word>
                <pc:TextEquiv>
                    <pc:Unicode>Tar-ry</pc:Unicode>
                </pc:TextEquiv>
            </pc:TextLine>
            <pc:TextLine id="line-5c79c325-27fa-4564-a499-8b15248efda7">
                <pc:Coords points="1325,1019 1396,1020 1396,1054 1325,1053"/>
                <pc:Word id="word-c9d84332-41d3-4618-97c3-727d3d049bba">
                    <pc:Coords points="1325,1019 1396,1020 1396,1054 1325,1053"/>
                    <pc:TextEquiv>
                        <pc:Unicode>not,</pc:Unicode>
                    </pc:TextEquiv>
                </pc:Word>
                <pc:TextEquiv>
                    <pc:Unicode>not,</pc:Unicode>
                </pc:TextEquiv>
            </pc:TextLine>
            <pc:TextLine id="line-c2795c35-0723-4ea4-a866-8bc4bb1f7022">
                <pc:Coords points="1440,1011 2362,1017 2362,1061 1440,1055"/>
                <pc:Word id="word-16421eeb-373f-4154-b289-a6d004eca254">
                    <pc:Coords points="1440,1019 1492,1019 1492,1046 1440,1045"/>
                    <pc:TextEquiv>
                        <pc:Unicode>tar</pc:Unicode>
                    </pc:TextEquiv>
                </pc:Word>
                <pc:Word id="word-c738e6b1-482f-4ea5-89a0-b19ab659b901">
                    <pc:Coords points="1507,1032 1519,1032 1519,1039 1507,1039"/>
                    <pc:TextEquiv>
                        <pc:Unicode>-</pc:Unicode>
                    </pc:TextEquiv>
                </pc:Word>
                <pc:Word id="word-d6c5c246-440d-4c7e-bff8-92545646d6c2">
                    <pc:Coords points="1535,1025 1573,1025 1573,1056 1535,1055"/>
                    <pc:TextEquiv>
                        <pc:Unicode>ry</pc:Unicode>
                    </pc:TextEquiv>
                </pc:Word>
                <pc:Word id="word-1d8d6b61-889b-4d3b-9e1c-254904fbb005">
                    <pc:Coords points="1616,1019 1687,1020 1687,1053 1616,1053"/>
                    <pc:TextEquiv>
                        <pc:Unicode>not,</pc:Unicode>
                    </pc:TextEquiv>
                </pc:Word>
                <pc:Word id="word-49def8ef-843a-4c4c-a326-b6c5c7471164">
                    <pc:Coords points="1711,1014 1819,1015 1819,1047 1711,1046"/>
                    <pc:TextEquiv>
                        <pc:Unicode>Come</pc:Unicode>
                    </pc:TextEquiv>
                </pc:Word>
                <pc:Word id="word-8f7f2272-415b-472d-aaf4-6bf73cc4af79">
                    <pc:Coords points="1847,1015 1916,1015 1916,1047 1847,1046"/>
                    <pc:TextEquiv>
                        <pc:Unicode>and</pc:Unicode>
                    </pc:TextEquiv>
                </pc:Word>
                <pc:Word id="word-ba454cd4-c6e6-4607-abf1-8b1de26a6f76">
                    <pc:Coords points="1929,1014 2010,1015 2010,1048 1929,1047"/>
                    <pc:TextEquiv>
                        <pc:Unicode>take</pc:Unicode>
                    </pc:TextEquiv>
                </pc:Word>
                <pc:Word id="word-280a70c4-4bff-4ae9-9048-1fa588046bb5">
                    <pc:Coords points="2038,1015 2092,1015 2092,1048 2038,1047"/>
                    <pc:TextEquiv>
                        <pc:Unicode>his</pc:Unicode>
                    </pc:TextEquiv>
                </pc:Word>
                <pc:Word id="word-dd99b0f9-3bbb-4ae5-9bc1-09203fa3254a">
                    <pc:Coords points="2107,1025 2197,1025 2198,1049 2107,1048"/>
                    <pc:TextEquiv>
                        <pc:Unicode>cross</pc:Unicode>
                    </pc:TextEquiv>
                </pc:Word>
                <pc:Word id="word-034ff8c5-94ea-4b95-b18f-565a4923fe45">
                    <pc:Coords points="2225,1020 2273,1021 2274,1049 2225,1049"/>
                    <pc:TextEquiv>
                        <pc:Unicode>to-</pc:Unicode>
                    </pc:TextEquiv>
                </pc:Word>
                <pc:Word id="word-cb255ac4-7fdf-4760-9c67-9c7a56fb15d3">
                    <pc:Coords points="2283,1017 2362,1017 2362,1059 2284,1058"/>
                    <pc:TextEquiv>
                        <pc:Unicode>day,</pc:Unicode>
                    </pc:TextEquiv>
                </pc:Word>
                <pc:TextEquiv>
                    <pc:Unicode>tar - ry not, Come and take his cross to- day,</pc:Unicode>
                </pc:TextEquiv>
            </pc:TextLine>
            <pc:TextLine id="line-a9e97cbc-bee5-45e6-b604-aea3903bcc16">
                <pc:Coords points="363,1076 395,1076 395,1102 363,1101"/>
                <pc:Word id="word-0018ea21-a158-4ff9-80ef-1d2963d8e2bd">
                    <pc:Coords points="363,1076 395,1076 395,1102 363,1101"/>
                    <pc:TextEquiv>
                        <pc:Unicode>2.</pc:Unicode>
                    </pc:TextEquiv>
                </pc:Word>
                <pc:TextEquiv>
                    <pc:Unicode>2.</pc:Unicode>
                </pc:TextEquiv>
            </pc:TextLine>
            <pc:TextLine id="line-48cdd10e-b13f-4df8-90c1-6f2bf37f904c">
                <pc:Coords points="442,1065 500,1066 500,1098 442,1097"/>
                <pc:Word id="word-ff65d524-f707-435f-85b4-a2f86ad4bf9a">
                    <pc:Coords points="442,1065 500,1066 500,1098 442,1097"/>
                    <pc:TextEquiv>
                        <pc:Unicode>He</pc:Unicode>
                    </pc:TextEquiv>
                </pc:Word>
                <pc:TextEquiv>
                    <pc:Unicode>He</pc:Unicode>
                </pc:TextEquiv>
            </pc:TextLine>
            <pc:TextLine id="line-cca44710-48a3-4d6e-b03e-084676c09a1f">
                <pc:Coords points="572,1066 602,1066 602,1097 572,1096"/>
                <pc:Word id="word-8c1f27af-cb2b-4cb0-aebe-f103dbdb6dfe">
                    <pc:Coords points="572,1066 602,1066 602,1097 572,1096"/>
                    <pc:TextEquiv>
                        <pc:Unicode>is</pc:Unicode>
                    </pc:TextEquiv>
                </pc:Word>
                <pc:TextEquiv>
                    <pc:Unicode>is</pc:Unicode>
                </pc:TextEquiv>
            </pc:TextLine>
            <pc:TextLine id="line-bdd908c7-0475-4161-ac3f-68621e47190a">
                <pc:Coords points="655,1063 802,1064 801,1106 655,1105"/>
                <pc:Word id="word-01e9629e-1c63-4abe-9ce2-883801c0f0a1">
                    <pc:Coords points="655,1063 802,1064 801,1106 655,1105"/>
                    <pc:TextEquiv>
                        <pc:Unicode>will-ing</pc:Unicode>
                    </pc:TextEquiv>
                </pc:Word>
                <pc:TextEquiv>
                    <pc:Unicode>will-ing</pc:Unicode>
                </pc:TextEquiv>
            </pc:TextLine>
            <pc:TextLine id="line-fa111bb4-eaf9-47e2-a85d-1c810c7f8154">
                <pc:Coords points="845,1067 880,1067 880,1095 844,1094"/>
                <pc:Word id="word-dbc6e14e-9fdb-470c-b859-b2f3f57bc5b2">
                    <pc:Coords points="845,1067 880,1067 880,1095 844,1094"/>
                    <pc:TextEquiv>
                        <pc:Unicode>to</pc:Unicode>
                    </pc:TextEquiv>
                </pc:Word>
                <pc:TextEquiv>
                    <pc:Unicode>to</pc:Unicode>
                </pc:TextEquiv>
            </pc:TextLine>
            <pc:TextLine id="line-dedace0b-0344-4c8c-8560-2f33f6e8e51a">
                <pc:Coords points="968,1061 1124,1062 1124,1103 968,1102"/>
                <pc:Word id="word-8fdf6895-2aff-454d-a0ee-a7183103c636">
                    <pc:Coords points="968,1061 1124,1062 1124,1103 968,1102"/>
                    <pc:TextEquiv>
                        <pc:Unicode>for-give,</pc:Unicode>
                    </pc:TextEquiv>
                </pc:Word>
                <pc:TextEquiv>
                    <pc:Unicode>for-give,</pc:Unicode>
                </pc:TextEquiv>
            </pc:TextLine>
            <pc:TextLine id="line-c520f986-d7a0-470f-aab5-0c3bedf772e8">
                <pc:Coords points="1163,1059 1284,1060 1284,1099 1163,1099"/>
                <pc:Word id="word-90f46750-2eec-4c04-bbd5-86c1986ddc68">
                    <pc:Coords points="1163,1059 1284,1060 1284,1099 1163,1099"/>
                    <pc:TextEquiv>
                        <pc:Unicode>Tar-ry</pc:Unicode>
                    </pc:TextEquiv>
                </pc:Word>
                <pc:TextEquiv>
                    <pc:Unicode>Tar-ry</pc:Unicode>
                </pc:TextEquiv>
            </pc:TextLine>
            <pc:TextLine id="line-484bce9b-a1b2-4eb8-9ef2-145e03297a86">
                <pc:Coords points="1326,1063 1396,1064 1396,1098 1326,1098"/>
                <pc:Word id="word-df5fb2a1-7d29-4d21-9566-7474d58588d3">
                    <pc:Coords points="1326,1063 1396,1064 1396,1098 1326,1098"/>
                    <pc:TextEquiv>
                        <pc:Unicode>not,</pc:Unicode>
                    </pc:TextEquiv>
                </pc:Word>
                <pc:TextEquiv>
                    <pc:Unicode>not,</pc:Unicode>
                </pc:TextEquiv>
            </pc:TextLine>
            <pc:TextLine id="line-73a7387a-9f8c-4c22-ac9e-1ef7f4499c2e">
                <pc:Coords points="1440,1055 2363,1061 2364,1105 1440,1099"/>
                <pc:Word id="word-0f14b8a8-567d-4e3b-b579-a4678da88939">
                    <pc:Coords points="1440,1064 1491,1064 1491,1091 1440,1091"/>
                    <pc:TextEquiv>
                        <pc:Unicode>tar</pc:Unicode>
                    </pc:TextEquiv>
                </pc:Word>
                <pc:Word id="word-ffdebe7e-593f-4980-a31b-2bb38a998f47">
                    <pc:Coords points="1506,1077 1517,1077 1517,1083 1506,1083"/>
                    <pc:TextEquiv>
                        <pc:Unicode>-</pc:Unicode>
                    </pc:TextEquiv>
                </pc:Word>
                <pc:Word id="word-592b5063-e3fe-471a-85e5-e5339fcec4d7">
                    <pc:Coords points="1533,1068 1572,1068 1572,1100 1533,1100"/>
                    <pc:TextEquiv>
                        <pc:Unicode>ry</pc:Unicode>
                    </pc:TextEquiv>
                </pc:Word>
                <pc:Word id="word-7f149c3c-b127-4dea-81f2-d8e1303d002b">
                    <pc:Coords points="1616,1063 1686,1064 1686,1098 1616,1097"/>
                    <pc:TextEquiv>
                        <pc:Unicode>not,</pc:Unicode>
                    </pc:TextEquiv>
                </pc:Word>
                <pc:Word id="word-0fdc98a4-cc93-493b-ab5a-ccffe3c734fc">
                    <pc:Coords points="1710,1059 1789,1059 1789,1090 1710,1090"/>
                    <pc:TextEquiv>
                        <pc:Unicode>You</pc:Unicode>
                    </pc:TextEquiv>
                </pc:Word>
                <pc:Word id="word-94c35ddf-e8d9-4715-9205-a51ee1f9b3d1">
                    <pc:Coords points="1831,1069 1908,1069 1909,1100 1831,1100"/>
                    <pc:TextEquiv>
                        <pc:Unicode>may</pc:Unicode>
                    </pc:TextEquiv>
                </pc:Word>
                <pc:Word id="word-8514d56f-726b-46fa-bce0-de58979f0515">
                    <pc:Coords points="1924,1068 2020,1069 2020,1092 1924,1092"/>
                    <pc:TextEquiv>
                        <pc:Unicode>come</pc:Unicode>
                    </pc:TextEquiv>
                </pc:Word>
                <pc:Word id="word-87cc9f8b-4a07-47ce-a5dd-55f286da5bba">
                    <pc:Coords points="2033,1064 2070,1064 2070,1092 2033,1091"/>
                    <pc:TextEquiv>
                        <pc:Unicode>to</pc:Unicode>
                    </pc:TextEquiv>
                </pc:Word>
                <pc:Word id="word-857454d1-0248-4292-b361-fa3df18bc7ff">
                    <pc:Coords points="2100,1060 2170,1060 2170,1092 2100,1091"/>
                    <pc:TextEquiv>
                        <pc:Unicode>him</pc:Unicode>
                    </pc:TextEquiv>
                </pc:Word>
                <pc:Word id="word-14b076e0-3f5e-43fa-ab48-243c3389757d">
                    <pc:Coords points="2199,1060 2268,1061 2268,1093 2199,1093"/>
                    <pc:TextEquiv>
                        <pc:Unicode>and</pc:Unicode>
                    </pc:TextEquiv>
                </pc:Word>
                <pc:Word id="word-2b863088-48e3-48c3-8347-2da76af53a45">
                    <pc:Coords points="2281,1061 2363,1061 2364,1101 2281,1101"/>
                    <pc:TextEquiv>
                        <pc:Unicode>live,</pc:Unicode>
                    </pc:TextEquiv>
                </pc:Word>
                <pc:TextEquiv>
                    <pc:Unicode>tar - ry not, You may come to him and live,</pc:Unicode>
                </pc:TextEquiv>
            </pc:TextLine>
            <pc:TextLine id="line-d706924d-77dc-489d-bc7f-ce3e715e267d">
                <pc:Coords points="362,1120 395,1120 395,1154 362,1153"/>
                <pc:Word id="word-5f55ba80-ab7d-4701-a33b-4657140325b9">
                    <pc:Coords points="362,1120 395,1120 395,1154 362,1153"/>
                    <pc:TextEquiv>
                        <pc:Unicode>3.</pc:Unicode>
                    </pc:TextEquiv>
                </pc:Word>
                <pc:TextEquiv>
                    <pc:Unicode>3.</pc:Unicode>
                </pc:TextEquiv>
            </pc:TextLine>
            <pc:TextLine id="line-3c058ccf-3b96-4e7a-860f-ce32afbc23bc">
                <pc:Coords points="440,1092 2436,1106 2436,1166 439,1151"/>
                <pc:Word id="word-635b4926-6483-4c96-ad41-663b4ce93833">
                    <pc:Coords points="440,1108 588,1109 587,1153 439,1151"/>
                    <pc:TextEquiv>
                        <pc:Unicode>Though</pc:Unicode>
                    </pc:TextEquiv>
                </pc:Word>
                <pc:Word id="word-962b2fa9-9f95-4b52-be44-5c3872d2dc86">
                    <pc:Coords points="601,1107 669,1108 669,1141 601,1141"/>
                    <pc:TextEquiv>
                        <pc:Unicode>this</pc:Unicode>
                    </pc:TextEquiv>
                </pc:Word>
                <pc:Word id="word-5c9fd20c-de26-4155-918c-264bd448923a">
                    <pc:Coords points="684,1107 793,1108 793,1141 684,1140"/>
                    <pc:TextEquiv>
                        <pc:Unicode>world</pc:Unicode>
                    </pc:TextEquiv>
                </pc:Word>
                <pc:Word id="word-04dc53ce-0cae-4d9f-b6ff-56212fca35f3">
                    <pc:Coords points="807,1107 851,1107 851,1140 807,1140"/>
                    <pc:TextEquiv>
                        <pc:Unicode>be</pc:Unicode>
                    </pc:TextEquiv>
                </pc:Word>
                <pc:Word id="word-0165c8be-ae96-4f73-a7b9-bdb594775881">
                    <pc:Coords points="864,1105 978,1106 978,1149 864,1148"/>
                    <pc:TextEquiv>
                        <pc:Unicode>bright</pc:Unicode>
                    </pc:TextEquiv>
                </pc:Word>
                <pc:Word id="word-1b2ab352-d357-4e26-ab64-2f1cc4e8f676">
                    <pc:Coords points="992,1105 1060,1105 1060,1137 992,1137"/>
                    <pc:TextEquiv>
                        <pc:Unicode>and</pc:Unicode>
                    </pc:TextEquiv>
                </pc:Word>
                <pc:Word id="word-3f39748c-cd55-4689-b06d-39bcbc37eb8d">
                    <pc:Coords points="1075,1104 1150,1104 1150,1143 1075,1143"/>
                    <pc:TextEquiv>
                        <pc:Unicode>fair,</pc:Unicode>
                    </pc:TextEquiv>
                </pc:Word>
                <pc:Word id="word-ccc96573-5c64-45cd-af8e-71af34510105">
                    <pc:Coords points="1163,1104 1283,1104 1283,1145 1163,1145"/>
                    <pc:TextEquiv>
                        <pc:Unicode>Tar-ry</pc:Unicode>
                    </pc:TextEquiv>
                </pc:Word>
                <pc:Word id="word-12f6f7a3-4d7b-4051-a18f-3624b81ce9ff">
                    <pc:Coords points="1325,1107 1396,1108 1396,1143 1325,1142"/>
                    <pc:TextEquiv>
                        <pc:Unicode>not,</pc:Unicode>
                    </pc:TextEquiv>
                </pc:Word>
                <pc:Word id="word-357820f6-a54c-4f62-91c3-29fe9fd3b348">
                    <pc:Coords points="1440,1107 1492,1108 1492,1135 1440,1135"/>
                    <pc:TextEquiv>
                        <pc:Unicode>tar</pc:Unicode>
                    </pc:TextEquiv>
                </pc:Word>
                <pc:Word id="word-7705d3af-5016-4ae0-b646-fd06f36edcfc">
                    <pc:Coords points="1507,1121 1519,1121 1519,1128 1507,1128"/>
                    <pc:TextEquiv>
                        <pc:Unicode>-</pc:Unicode>
                    </pc:TextEquiv>
                </pc:Word>
                <pc:Word id="word-a2e2e274-0e2b-4b8d-8176-a78ed3d2d466">
                    <pc:Coords points="1535,1113 1573,1113 1573,1144 1535,1144"/>
                    <pc:TextEquiv>
                        <pc:Unicode>ry</pc:Unicode>
                    </pc:TextEquiv>
                </pc:Word>
                <pc:Word id="word-85b37354-306f-4e4d-9b05-97538ac27969">
                    <pc:Coords points="1617,1107 1689,1107 1689,1141 1617,1140"/>
                    <pc:TextEquiv>
                        <pc:Unicode>not,</pc:Unicode>
                    </pc:TextEquiv>
                </pc:Word>
                <pc:Word id="word-455167d3-58c2-4158-9f8f-42d8bc1c0b30">
                    <pc:Coords points="1710,1102 1829,1103 1829,1145 1710,1144"/>
                    <pc:TextEquiv>
                        <pc:Unicode>Bright</pc:Unicode>
                    </pc:TextEquiv>
                </pc:Word>
                <pc:Word id="word-3557174b-2554-42c9-b0d8-c84a965709fa">
                    <pc:Coords points="1874,1114 1910,1114 1910,1135 1874,1134"/>
                    <pc:TextEquiv>
                        <pc:Unicode>er</pc:Unicode>
                    </pc:TextEquiv>
                </pc:Word>
                <pc:Word id="word-0a71b32b-b116-48a0-b5c4-bfb6b896157e">
                    <pc:Coords points="1954,1104 1984,1104 1984,1136 1954,1135"/>
                    <pc:TextEquiv>
                        <pc:Unicode>is</pc:Unicode>
                    </pc:TextEquiv>
                </pc:Word>
                <pc:Word id="word-1398ca7b-ed17-465e-ab56-d811ae4539f7">
                    <pc:Coords points="2028,1113 2090,1114 2090,1136 2028,1136"/>
                    <pc:TextEquiv>
                        <pc:Unicode>our</pc:Unicode>
                    </pc:TextEquiv>
                </pc:Word>
                <pc:Word id="word-c4f7b7e8-8438-4dba-bba3-6a7043bdcb9e">
                    <pc:Coords points="2104,1104 2205,1104 2206,1137 2104,1137"/>
                    <pc:TextEquiv>
                        <pc:Unicode>home</pc:Unicode>
                    </pc:TextEquiv>
                </pc:Word>
                <pc:Word id="word-7f824381-bece-44fa-b4ee-f78129c1007e">
                    <pc:Coords points="2222,1108 2291,1109 2292,1148 2222,1148"/>
                    <pc:TextEquiv>
                        <pc:Unicode>"up</pc:Unicode>
                    </pc:TextEquiv>
                </pc:Word>
                <pc:Word id="word-7af8ef07-9a4c-4509-8ae2-495156501ce6">
                    <pc:Coords points="2303,1105 2436,1106 2436,1146 2303,1145"/>
                    <pc:TextEquiv>
                        <pc:Unicode>there,"</pc:Unicode>
                    </pc:TextEquiv>
                </pc:Word>
                <pc:TextEquiv>
                    <pc:Unicode>Though this world be bright and fair, Tar-ry not, tar - ry not, Bright er is our home "up there,"</pc:Unicode>
                </pc:TextEquiv>
            </pc:TextLine>
            <pc:TextLine id="line-aecf8c3a-6128-439c-be22-6554fab75764">
                <pc:Coords points="2226,1434 2364,1435 2364,1470 2226,1469"/>
                <pc:Word id="word-a8c93349-1714-407d-8623-555d81b4520e">
                    <pc:Coords points="2226,1434 2364,1435 2364,1470 2226,1469"/>
                    <pc:TextEquiv>
                        <pc:Unicode>Ritard.</pc:Unicode>
                    </pc:TextEquiv>
                </pc:Word>
                <pc:TextEquiv>
                    <pc:Unicode>Ritard.</pc:Unicode>
                </pc:TextEquiv>
            </pc:TextLine>
            <pc:TextLine id="line-0076148a-0e16-45c0-a434-8ad0aa97615d">
                <pc:Coords points="2373,1529 2399,1529 2399,1568 2373,1568"/>
                <pc:Word id="word-e2400173-c318-4f71-b22e-e363e951a6ed">
                    <pc:Coords points="2373,1529 2399,1529 2399,1568 2373,1568"/>
                    <pc:TextEquiv>
                        <pc:Unicode>of</pc:Unicode>
                    </pc:TextEquiv>
                </pc:Word>
                <pc:TextEquiv>
                    <pc:Unicode>of</pc:Unicode>
                </pc:TextEquiv>
            </pc:TextLine>
            <pc:TextLine id="line-1cc85961-6666-4f55-ad57-0bb39eb2d0ba">
                <pc:Coords points="597,1644 669,1645 669,1678 597,1678"/>
                <pc:Word id="word-b32e0a74-eeb0-4f77-9c18-a8742cad759e">
                    <pc:Coords points="597,1644 669,1645 669,1678 597,1678"/>
                    <pc:TextEquiv>
                        <pc:Unicode>not,</pc:Unicode>
                    </pc:TextEquiv>
                </pc:Word>
                <pc:TextEquiv>
                    <pc:Unicode>not,</pc:Unicode>
                </pc:TextEquiv>
            </pc:TextLine>
            <pc:TextLine id="line-b7b91e83-c396-4a88-95e5-491ed840d8ea">
                <pc:Coords points="728,1643 863,1644 863,1679 728,1677"/>
                <pc:Word id="word-5e73f373-4bae-4210-ba45-ca3cc689bbc0">
                    <pc:Coords points="728,1643 780,1643 780,1671 728,1670"/>
                    <pc:TextEquiv>
                        <pc:Unicode>tar</pc:Unicode>
                    </pc:TextEquiv>
                </pc:Word>
                <pc:Word id="word-f2a44cdf-a78b-47ef-ae2f-ae892b79bf43">
                    <pc:Coords points="794,1656 806,1656 806,1662 794,1662"/>
                    <pc:TextEquiv>
                        <pc:Unicode>-</pc:Unicode>
                    </pc:TextEquiv>
                </pc:Word>
                <pc:Word id="word-be8d888d-699d-48fd-9590-3c3c26775796">
                    <pc:Coords points="823,1646 863,1647 863,1679 823,1678"/>
                    <pc:TextEquiv>
                        <pc:Unicode>ry</pc:Unicode>
                    </pc:TextEquiv>
                </pc:Word>
                <pc:TextEquiv>
                    <pc:Unicode>tar - ry</pc:Unicode>
                </pc:TextEquiv>
            </pc:TextLine>
            <pc:TextLine id="line-1035d9e8-2c9a-477e-ba7f-79ccdd6732b5">
                <pc:Coords points="908,1640 988,1641 988,1674 908,1673"/>
                <pc:Word id="word-5955b428-6106-4464-ac30-f48c99128775">
                    <pc:Coords points="908,1640 988,1641 988,1674 908,1673"/>
                    <pc:TextEquiv>
                        <pc:Unicode>not;</pc:Unicode>
                    </pc:TextEquiv>
                </pc:Word>
                <pc:TextEquiv>
                    <pc:Unicode>not;</pc:Unicode>
                </pc:TextEquiv>
            </pc:TextLine>
            <pc:TextLine id="line-3185112b-d589-4772-8db0-009983d4d231">
                <pc:Coords points="1005,1636 1110,1637 1110,1668 1004,1667"/>
                <pc:Word id="word-76c42be4-42e1-4683-8686-7c34dd6cefd3">
                    <pc:Coords points="1005,1636 1110,1637 1110,1668 1004,1667"/>
                    <pc:TextEquiv>
                        <pc:Unicode>Come</pc:Unicode>
                    </pc:TextEquiv>
                </pc:Word>
                <pc:TextEquiv>
                    <pc:Unicode>Come</pc:Unicode>
                </pc:TextEquiv>
            </pc:TextLine>
            <pc:TextLine id="line-1bfa1d5c-e96a-4f6b-a171-fa1b34660819">
                <pc:Coords points="1138,1634 1208,1635 1208,1666 1138,1666"/>
                <pc:Word id="word-46a65980-944c-46c7-93b4-15d9757bf5b4">
                    <pc:Coords points="1138,1634 1208,1635 1208,1666 1138,1666"/>
                    <pc:TextEquiv>
                        <pc:Unicode>and</pc:Unicode>
                    </pc:TextEquiv>
                </pc:Word>
                <pc:TextEquiv>
                    <pc:Unicode>and</pc:Unicode>
                </pc:TextEquiv>
            </pc:TextLine>
            <pc:TextLine id="line-d44488b5-4de8-4c1f-a19b-1bfc4cdaab1e">
                <pc:Coords points="1222,1634 1302,1634 1302,1666 1221,1666"/>
                <pc:Word id="word-4ff3a5ee-8252-4991-aa12-f8e4d8e2d41d">
                    <pc:Coords points="1222,1634 1302,1634 1302,1666 1221,1666"/>
                    <pc:TextEquiv>
                        <pc:Unicode>take</pc:Unicode>
                    </pc:TextEquiv>
                </pc:Word>
                <pc:TextEquiv>
                    <pc:Unicode>take</pc:Unicode>
                </pc:TextEquiv>
            </pc:TextLine>
            <pc:TextLine id="line-a8b4b71c-646b-4a9b-9da2-e7ee3f2e5d78">
                <pc:Coords points="1345,1633 1399,1633 1399,1666 1345,1665"/>
                <pc:Word id="word-64b0bd3c-3a3d-492b-844c-a2b4db3beec9">
                    <pc:Coords points="1345,1633 1399,1633 1399,1666 1345,1665"/>
                    <pc:TextEquiv>
                        <pc:Unicode>his</pc:Unicode>
                    </pc:TextEquiv>
                </pc:Word>
                <pc:TextEquiv>
                    <pc:Unicode>his</pc:Unicode>
                </pc:TextEquiv>
            </pc:TextLine>
            <pc:TextLine id="line-bc22520a-c2f8-4bb4-8d8a-3b7ad9a9c74d">
                <pc:Coords points="1444,1641 1535,1642 1535,1667 1444,1666"/>
                <pc:Word id="word-fa17df18-8ca0-4613-8383-6a264aa02775">
                    <pc:Coords points="1444,1641 1535,1642 1535,1667 1444,1666"/>
                    <pc:TextEquiv>
                        <pc:Unicode>cross</pc:Unicode>
                    </pc:TextEquiv>
                </pc:Word>
                <pc:TextEquiv>
                    <pc:Unicode>cross</pc:Unicode>
                </pc:TextEquiv>
            </pc:TextLine>
            <pc:TextLine id="line-beb5dbfb-d688-40b3-93a5-8eb0739e8fee">
                <pc:Coords points="1594,1638 1630,1638 1630,1666 1594,1666"/>
                <pc:Word id="word-517e85e3-e112-4003-9f53-4ee99b5ba70b">
                    <pc:Coords points="1594,1638 1630,1638 1630,1666 1594,1666"/>
                    <pc:TextEquiv>
                        <pc:Unicode>to</pc:Unicode>
                    </pc:TextEquiv>
                </pc:Word>
                <pc:TextEquiv>
                    <pc:Unicode>to</pc:Unicode>
                </pc:TextEquiv>
            </pc:TextLine>
            <pc:TextLine id="line-87c618bd-581b-4386-ba5e-d16f49a9d77e">
                <pc:Coords points="1646,1651 1657,1651 1658,1658 1646,1658"/>
                <pc:Word id="word-67198556-8963-47a0-bc1f-6159fe27e140">
                    <pc:Coords points="1646,1651 1657,1651 1658,1658 1646,1658"/>
                    <pc:TextEquiv>
                        <pc:Unicode>-</pc:Unicode>
                    </pc:TextEquiv>
                </pc:Word>
                <pc:TextEquiv>
                    <pc:Unicode>-</pc:Unicode>
                </pc:TextEquiv>
            </pc:TextLine>
            <pc:TextLine id="line-45b26d4f-8707-43e6-a28f-efba3e80a4bd">
                <pc:Coords points="1674,1633 1752,1634 1752,1675 1674,1674"/>
                <pc:Word id="word-aa027fe1-084f-4cf4-8739-1e41dc068776">
                    <pc:Coords points="1674,1633 1752,1634 1752,1675 1674,1674"/>
                    <pc:TextEquiv>
                        <pc:Unicode>day,</pc:Unicode>
                    </pc:TextEquiv>
                </pc:Word>
                <pc:TextEquiv>
                    <pc:Unicode>day,</pc:Unicode>
                </pc:TextEquiv>
            </pc:TextLine>
            <pc:TextLine id="line-8968eb3d-4207-4588-9d6f-e4ee8197e604">
                <pc:Coords points="1798,1633 1870,1634 1870,1666 1798,1666"/>
                <pc:Word id="word-c9f05fc6-6d4e-4848-a486-f873d84ae18a">
                    <pc:Coords points="1798,1633 1870,1634 1870,1666 1798,1666"/>
                    <pc:TextEquiv>
                        <pc:Unicode>Tar</pc:Unicode>
                    </pc:TextEquiv>
                </pc:Word>
                <pc:TextEquiv>
                    <pc:Unicode>Tar</pc:Unicode>
                </pc:TextEquiv>
            </pc:TextLine>
            <pc:TextLine id="line-19aafce6-381a-4773-bb64-2e428fbc4218">
                <pc:Coords points="415,1645 568,1646 568,1683 414,1682"/>
                <pc:Word id="word-0a26d9bd-55fd-44a1-a6e4-96da3d32c305">
                    <pc:Coords points="415,1645 487,1645 487,1677 415,1676"/>
                    <pc:TextEquiv>
                        <pc:Unicode>Tar</pc:Unicode>
                    </pc:TextEquiv>
                </pc:Word>
                <pc:Word id="word-326fa79c-28c0-481a-b433-6ced2b78126e">
                    <pc:Coords points="502,1661 512,1661 512,1666 502,1666"/>
                    <pc:TextEquiv>
                        <pc:Unicode>-</pc:Unicode>
                    </pc:TextEquiv>
                </pc:Word>
                <pc:Word id="word-2454b3e3-63d4-444e-b823-0ec5ff47b2c4">
                    <pc:Coords points="530,1651 568,1652 568,1683 530,1683"/>
                    <pc:TextEquiv>
                        <pc:Unicode>ry</pc:Unicode>
                    </pc:TextEquiv>
                </pc:Word>
                <pc:TextEquiv>
                    <pc:Unicode>Tar - ry</pc:Unicode>
                </pc:TextEquiv>
            </pc:TextLine>
            <pc:TextLine id="line-6d95935e-155a-41ef-8a28-279ac44f3cf8">
                <pc:Coords points="1910,1643 1947,1643 1948,1675 1910,1675"/>
                <pc:Word id="word-ddaa14b5-9b76-4325-a883-105a467b64c8">
                    <pc:Coords points="1910,1643 1947,1643 1948,1675 1910,1675"/>
                    <pc:TextEquiv>
                        <pc:Unicode>ry</pc:Unicode>
                    </pc:TextEquiv>
                </pc:Word>
                <pc:TextEquiv>
                    <pc:Unicode>ry</pc:Unicode>
                </pc:TextEquiv>
            </pc:TextLine>
            <pc:TextLine id="line-8dcfe6f2-bf99-45d6-a7e6-f5d412198fa4">
                <pc:Coords points="1985,1638 2058,1639 2058,1674 1986,1673"/>
                <pc:Word id="word-5ff60fbd-80fd-44f4-a4fa-9357631447b1">
                    <pc:Coords points="1985,1638 2058,1639 2058,1674 1986,1673"/>
                    <pc:TextEquiv>
                        <pc:Unicode>not,</pc:Unicode>
                    </pc:TextEquiv>
                </pc:Word>
                <pc:TextEquiv>
                    <pc:Unicode>not,</pc:Unicode>
                </pc:TextEquiv>
            </pc:TextLine>
            <pc:TextLine id="line-f5176cf2-fcb7-4ec7-81c2-2b6cfec5e387">
                <pc:Coords points="2116,1641 2249,1642 2250,1680 2117,1679"/>
                <pc:Word id="word-6dee3685-df98-4c56-92e8-b1e62ae54ade">
                    <pc:Coords points="2116,1641 2169,1641 2169,1669 2117,1668"/>
                    <pc:TextEquiv>
                        <pc:Unicode>tar</pc:Unicode>
                    </pc:TextEquiv>
                </pc:Word>
                <pc:Word id="word-1da365c3-0143-413e-a810-0803c8b9a319">
                    <pc:Coords points="2183,1654 2197,1654 2197,1662 2183,1662"/>
                    <pc:TextEquiv>
                        <pc:Unicode>-</pc:Unicode>
                    </pc:TextEquiv>
                </pc:Word>
                <pc:Word id="word-8dda7d06-6979-4369-9346-41422eacf424">
                    <pc:Coords points="2212,1646 2249,1646 2250,1680 2212,1679"/>
                    <pc:TextEquiv>
                        <pc:Unicode>ry</pc:Unicode>
                    </pc:TextEquiv>
                </pc:Word>
                <pc:TextEquiv>
                    <pc:Unicode>tar - ry</pc:Unicode>
                </pc:TextEquiv>
            </pc:TextLine>
            <pc:TextLine id="line-f616a66d-ad5e-48ff-b48f-5a469a8df780">
                <pc:Coords points="2293,1645 2364,1646 2364,1673 2294,1673"/>
                <pc:Word id="word-7523799a-e67c-44e0-a8c0-499b85db83e8">
                    <pc:Coords points="2293,1645 2364,1646 2364,1673 2294,1673"/>
                    <pc:TextEquiv>
                        <pc:Unicode>not.</pc:Unicode>
                    </pc:TextEquiv>
                </pc:Word>
                <pc:TextEquiv>
                    <pc:Unicode>not.</pc:Unicode>
                </pc:TextEquiv>
            </pc:TextLine>
            <pc:TextLine id="line-d674f2cd-9be7-406e-9cf7-ad8fc696ab12">
                <pc:Coords points="412,1687 662,1689 662,1729 412,1727"/>
                <pc:Word id="word-5283b87e-351d-41f1-9de8-1813d2a90daf">
                    <pc:Coords points="412,1687 480,1688 480,1721 412,1720"/>
                    <pc:TextEquiv>
                        <pc:Unicode>Tar</pc:Unicode>
                    </pc:TextEquiv>
                </pc:Word>
                <pc:Word id="word-f47bb6cf-256d-4a76-9ff6-69f13f6cfdcb">
                    <pc:Coords points="524,1695 562,1696 562,1728 523,1727"/>
                    <pc:TextEquiv>
                        <pc:Unicode>ry</pc:Unicode>
                    </pc:TextEquiv>
                </pc:Word>
                <pc:Word id="word-bc140d70-ed2b-4fe9-a5d0-8404d7632915">
                    <pc:Coords points="591,1688 662,1689 662,1723 591,1723"/>
                    <pc:TextEquiv>
                        <pc:Unicode>not,</pc:Unicode>
                    </pc:TextEquiv>
                </pc:Word>
                <pc:TextEquiv>
                    <pc:Unicode>Tar ry not,</pc:Unicode>
                </pc:TextEquiv>
            </pc:TextLine>
            <pc:TextLine id="line-5d580316-3b7a-40aa-b80c-0bc618b5a5af">
                <pc:Coords points="720,1678 1325,1683 1325,1727 720,1722"/>
                <pc:Word id="word-9d80189b-c80c-4d42-ac7e-311973a36a6c">
                    <pc:Coords points="720,1687 854,1688 854,1723 720,1722"/>
                    <pc:TextEquiv>
                        <pc:Unicode>tar - ry</pc:Unicode>
                    </pc:TextEquiv>
                </pc:Word>
                <pc:Word id="word-b07f98a6-6f2e-4712-bf01-09963ae33a0b">
                    <pc:Coords points="788,1699 800,1700 800,1707 788,1706"/>
                    <pc:TextEquiv>
                        <pc:Unicode>-</pc:Unicode>
                    </pc:TextEquiv>
                </pc:Word>
                <pc:Word id="word-882b22de-b7d4-4e88-bf32-399f345efb96">
                    <pc:Coords points="899,1685 977,1686 977,1719 899,1718"/>
                    <pc:TextEquiv>
                        <pc:Unicode>not;</pc:Unicode>
                    </pc:TextEquiv>
                </pc:Word>
                <pc:Word id="word-a3e05a42-5394-4180-a968-3bcc73524727">
                    <pc:Coords points="1011,1680 1088,1681 1088,1712 1011,1711"/>
                    <pc:TextEquiv>
                        <pc:Unicode>You</pc:Unicode>
                    </pc:TextEquiv>
                </pc:Word>
                <pc:Word id="word-ad763bbc-4d36-4779-97dc-cecd4d27cb41">
                    <pc:Coords points="1134,1688 1212,1689 1212,1720 1134,1720"/>
                    <pc:TextEquiv>
                        <pc:Unicode>may</pc:Unicode>
                    </pc:TextEquiv>
                </pc:Word>
                <pc:Word id="word-79b9ab12-7d29-4654-9327-a70a93effe6e">
                    <pc:Coords points="1227,1687 1325,1687 1325,1711 1227,1710"/>
                    <pc:TextEquiv>
                        <pc:Unicode>come</pc:Unicode>
                    </pc:TextEquiv>
                </pc:Word>
                <pc:TextEquiv>
                    <pc:Unicode>tar - ry - not; You may come</pc:Unicode>
                </pc:TextEquiv>
            </pc:TextLine>
            <pc:TextLine id="line-3382bb90-5326-42ef-a489-ccb83a7880ee">
                <pc:Coords points="1353,1681 1391,1682 1391,1710 1353,1710"/>
                <pc:Word id="word-82ee960e-dda8-45a6-b062-3103aab0f1f3">
                    <pc:Coords points="1353,1681 1391,1682 1391,1710 1353,1710"/>
                    <pc:TextEquiv>
                        <pc:Unicode>to</pc:Unicode>
                    </pc:TextEquiv>
                </pc:Word>
                <pc:TextEquiv>
                    <pc:Unicode>to</pc:Unicode>
                </pc:TextEquiv>
            </pc:TextLine>
            <pc:TextLine id="line-cbec9335-7927-4e20-a5c4-7ff99e0bf890">
                <pc:Coords points="1449,1677 1521,1678 1521,1710 1449,1709"/>
                <pc:Word id="word-64d6d17c-27b6-4a56-8032-8ed11b8ac785">
                    <pc:Coords points="1449,1677 1521,1678 1521,1710 1449,1709"/>
                    <pc:TextEquiv>
                        <pc:Unicode>him</pc:Unicode>
                    </pc:TextEquiv>
                </pc:Word>
                <pc:TextEquiv>
                    <pc:Unicode>him</pc:Unicode>
                </pc:TextEquiv>
            </pc:TextLine>
            <pc:TextLine id="line-9cbc573a-ffab-4ce4-aab5-fb97d3e8003a">
                <pc:Coords points="1575,1677 1643,1678 1643,1710 1575,1709"/>
                <pc:Word id="word-8b6ad886-99e2-45f9-8e1a-3058b2b85b16">
                    <pc:Coords points="1575,1677 1643,1678 1643,1710 1575,1709"/>
                    <pc:TextEquiv>
                        <pc:Unicode>and</pc:Unicode>
                    </pc:TextEquiv>
                </pc:Word>
                <pc:TextEquiv>
                    <pc:Unicode>and</pc:Unicode>
                </pc:TextEquiv>
            </pc:TextLine>
            <pc:TextLine id="line-3aff8329-9ec6-461a-a823-b9ba8fc86288">
                <pc:Coords points="1674,1677 1753,1678 1753,1717 1674,1717"/>
                <pc:Word id="word-ec04e3e5-fb43-43ed-8933-0a7d829ae9c2">
                    <pc:Coords points="1674,1677 1753,1678 1753,1717 1674,1717"/>
                    <pc:TextEquiv>
                        <pc:Unicode>live,</pc:Unicode>
                    </pc:TextEquiv>
                </pc:Word>
                <pc:TextEquiv>
                    <pc:Unicode>live,</pc:Unicode>
                </pc:TextEquiv>
            </pc:TextLine>
            <pc:TextLine id="line-e0c323b8-eace-49d8-831f-bb3d837a770c">
                <pc:Coords points="1793,1677 1866,1678 1866,1711 1793,1710"/>
                <pc:Word id="word-a40ee714-daff-4dd2-bc7d-1341d39b1b73">
                    <pc:Coords points="1793,1677 1866,1678 1866,1711 1793,1710"/>
                    <pc:TextEquiv>
                        <pc:Unicode>Tar</pc:Unicode>
                    </pc:TextEquiv>
                </pc:Word>
                <pc:TextEquiv>
                    <pc:Unicode>Tar</pc:Unicode>
                </pc:TextEquiv>
            </pc:TextLine>
            <pc:TextLine id="line-d7a2a501-adf5-466a-86cf-c02bdf995390">
                <pc:Coords points="1879,1695 1892,1695 1892,1702 1879,1702"/>
                <pc:Word id="word-6bd6732e-704d-43f9-8a42-83e304f960fb">
                    <pc:Coords points="1879,1695 1892,1695 1892,1702 1879,1702"/>
                    <pc:TextEquiv>
                        <pc:Unicode>-</pc:Unicode>
                    </pc:TextEquiv>
                </pc:Word>
                <pc:TextEquiv>
                    <pc:Unicode>-</pc:Unicode>
                </pc:TextEquiv>
            </pc:TextLine>
            <pc:TextLine id="line-4a196995-b1a1-4afe-977e-1f90a10ef22a">
                <pc:Coords points="1906,1687 1946,1688 1946,1720 1906,1720"/>
                <pc:Word id="word-71675019-e76d-4b13-9462-3de5893195a0">
                    <pc:Coords points="1906,1687 1946,1688 1946,1720 1906,1720"/>
                    <pc:TextEquiv>
                        <pc:Unicode>ry</pc:Unicode>
                    </pc:TextEquiv>
                </pc:Word>
                <pc:TextEquiv>
                    <pc:Unicode>ry</pc:Unicode>
                </pc:TextEquiv>
            </pc:TextLine>
            <pc:TextLine id="line-09d877e3-147a-456e-a80a-e52d06a945b6">
                <pc:Coords points="1983,1683 2056,1684 2056,1719 1983,1718"/>
                <pc:Word id="word-c07abeac-03c8-4e6e-8eb9-04d5d7d258b1">
                    <pc:Coords points="1983,1683 2056,1684 2056,1719 1983,1718"/>
                    <pc:TextEquiv>
                        <pc:Unicode>not,</pc:Unicode>
                    </pc:TextEquiv>
                </pc:Word>
                <pc:TextEquiv>
                    <pc:Unicode>not,</pc:Unicode>
                </pc:TextEquiv>
            </pc:TextLine>
            <pc:TextLine id="line-94318205-4024-4a5d-b947-43b891350971">
                <pc:Coords points="2115,1684 2248,1685 2249,1724 2115,1723"/>
                <pc:Word id="word-fcfea8db-9fd8-44d6-9f9a-41cebbde4444">
                    <pc:Coords points="2115,1684 2168,1685 2168,1714 2115,1713"/>
                    <pc:TextEquiv>
                        <pc:Unicode>tar</pc:Unicode>
                    </pc:TextEquiv>
                </pc:Word>
                <pc:Word id="word-e55ff59d-ca3d-4256-8178-fc5c4250d170">
                    <pc:Coords points="2181,1699 2193,1699 2193,1707 2181,1706"/>
                    <pc:TextEquiv>
                        <pc:Unicode>-</pc:Unicode>
                    </pc:TextEquiv>
                </pc:Word>
                <pc:Word id="word-6affbc78-3bfa-4785-8fd3-40da06d21f85">
                    <pc:Coords points="2209,1692 2248,1692 2249,1724 2209,1724"/>
                    <pc:TextEquiv>
                        <pc:Unicode>ry</pc:Unicode>
                    </pc:TextEquiv>
                </pc:Word>
                <pc:TextEquiv>
                    <pc:Unicode>tar - ry</pc:Unicode>
                </pc:TextEquiv>
            </pc:TextLine>
            <pc:TextLine id="line-0f90cab1-6f10-422f-9ea1-02fd6b293a9b">
                <pc:Coords points="2292,1688 2363,1689 2363,1718 2293,1718"/>
                <pc:Word id="word-dcec3415-382e-4950-ae31-4e654f4dc3ab">
                    <pc:Coords points="2292,1688 2363,1689 2363,1718 2293,1718"/>
                    <pc:TextEquiv>
                        <pc:Unicode>not.</pc:Unicode>
                    </pc:TextEquiv>
                </pc:Word>
                <pc:TextEquiv>
                    <pc:Unicode>not.</pc:Unicode>
                </pc:TextEquiv>
            </pc:TextLine>
            <pc:TextLine id="line-ea9ae303-881c-456c-a342-8e8a494a6f5a">
                <pc:Coords points="417,1733 487,1734 487,1765 417,1765"/>
                <pc:Word id="word-0a236673-1d2f-4837-bec2-6b9c4d031b2c">
                    <pc:Coords points="417,1733 487,1734 487,1765 417,1765"/>
                    <pc:TextEquiv>
                        <pc:Unicode>Tar</pc:Unicode>
                    </pc:TextEquiv>
                </pc:Word>
                <pc:TextEquiv>
                    <pc:Unicode>Tar</pc:Unicode>
                </pc:TextEquiv>
            </pc:TextLine>
            <pc:TextLine id="line-131c5268-09e4-4d49-804d-ea9ff0e12e46">
                <pc:Coords points="528,1740 565,1740 565,1771 527,1771"/>
                <pc:Word id="word-f622e46d-32a3-426a-a406-af89bcac692c">
                    <pc:Coords points="528,1740 565,1740 565,1771 527,1771"/>
                    <pc:TextEquiv>
                        <pc:Unicode>ry</pc:Unicode>
                    </pc:TextEquiv>
                </pc:Word>
                <pc:TextEquiv>
                    <pc:Unicode>ry</pc:Unicode>
                </pc:TextEquiv>
            </pc:TextLine>
            <pc:TextLine id="line-e50f3c49-2272-4312-b96f-89d8be7512b0">
                <pc:Coords points="595,1733 667,1734 667,1767 595,1767"/>
                <pc:Word id="word-51c08067-409c-40cd-a1d8-7748214fab51">
                    <pc:Coords points="595,1733 667,1734 667,1767 595,1767"/>
                    <pc:TextEquiv>
                        <pc:Unicode>not,</pc:Unicode>
                    </pc:TextEquiv>
                </pc:Word>
                <pc:TextEquiv>
                    <pc:Unicode>not,</pc:Unicode>
                </pc:TextEquiv>
            </pc:TextLine>
            <pc:TextLine id="line-6d60d5cc-b5b3-4621-9e96-6cfdbb10729d">
                <pc:Coords points="727,1713 2363,1727 2364,1781 727,1766"/>
                <pc:Word id="word-490db079-ce33-4716-9e81-094cbdbf4299">
                    <pc:Coords points="727,1731 860,1732 860,1768 727,1766"/>
                    <pc:TextEquiv>
                        <pc:Unicode>tar-ry</pc:Unicode>
                    </pc:TextEquiv>
                </pc:Word>
                <pc:Word id="word-d7ce22b8-ab82-45af-bde1-d278e0dda711">
                    <pc:Coords points="793,1744 806,1744 806,1751 793,1750"/>
                    <pc:TextEquiv>
                        <pc:Unicode>-</pc:Unicode>
                    </pc:TextEquiv>
                </pc:Word>
                <pc:Word id="word-2a73b881-a009-407a-9792-88109dfd19ee">
                    <pc:Coords points="899,1728 979,1729 978,1764 899,1763"/>
                    <pc:TextEquiv>
                        <pc:Unicode>not;</pc:Unicode>
                    </pc:TextEquiv>
                </pc:Word>
                <pc:Word id="word-2c1578d9-e049-4d18-82ce-41ecd528f747">
                    <pc:Coords points="1012,1723 1132,1724 1132,1767 1011,1766"/>
                    <pc:TextEquiv>
                        <pc:Unicode>Bright</pc:Unicode>
                    </pc:TextEquiv>
                </pc:Word>
                <pc:Word id="word-0028a65c-91f2-4f29-a130-cd8eb862f4a3">
                    <pc:Coords points="1147,1741 1158,1741 1158,1747 1147,1746"/>
                    <pc:TextEquiv>
                        <pc:Unicode>-</pc:Unicode>
                    </pc:TextEquiv>
                </pc:Word>
                <pc:Word id="word-a7a8eab3-ddbc-422c-960f-07caac449457">
                    <pc:Coords points="1177,1731 1214,1731 1214,1754 1177,1754"/>
                    <pc:TextEquiv>
                        <pc:Unicode>er</pc:Unicode>
                    </pc:TextEquiv>
                </pc:Word>
                <pc:Word id="word-6e51d59b-2de1-4cae-b444-186b8fba7ecf">
                    <pc:Coords points="1243,1722 1273,1722 1273,1755 1243,1754"/>
                    <pc:TextEquiv>
                        <pc:Unicode>is</pc:Unicode>
                    </pc:TextEquiv>
                </pc:Word>
                <pc:Word id="word-424b6ffa-febb-43f0-83ef-f88b92e94e58">
                    <pc:Coords points="1346,1731 1408,1731 1408,1754 1346,1754"/>
                    <pc:TextEquiv>
                        <pc:Unicode>our</pc:Unicode>
                    </pc:TextEquiv>
                </pc:Word>
                <pc:Word id="word-c773c2d6-a340-4ac4-8392-a23c2240085a">
                    <pc:Coords points="1452,1721 1554,1722 1554,1754 1452,1754"/>
                    <pc:TextEquiv>
                        <pc:Unicode>home</pc:Unicode>
                    </pc:TextEquiv>
                </pc:Word>
                <pc:Word id="word-854e3e18-25e4-4bfc-940e-e970b37f6b6a">
                    <pc:Coords points="1569,1724 1641,1725 1641,1764 1569,1764"/>
                    <pc:TextEquiv>
                        <pc:Unicode>"up</pc:Unicode>
                    </pc:TextEquiv>
                </pc:Word>
                <pc:Word id="word-3627681f-a15f-4bb6-84e8-af556cd9337a">
                    <pc:Coords points="1654,1721 1782,1722 1782,1762 1654,1761"/>
                    <pc:TextEquiv>
                        <pc:Unicode>there,"</pc:Unicode>
                    </pc:TextEquiv>
                </pc:Word>
                <pc:Word id="word-b87c1389-6897-4429-a3bf-a165e7c38836">
                    <pc:Coords points="1800,1722 1868,1723 1868,1755 1800,1754"/>
                    <pc:TextEquiv>
                        <pc:Unicode>Tar</pc:Unicode>
                    </pc:TextEquiv>
                </pc:Word>
                <pc:Word id="word-d006e29b-9c01-4949-b089-5fba0f21a18d">
                    <pc:Coords points="1882,1740 1895,1740 1895,1747 1882,1747"/>
                    <pc:TextEquiv>
                        <pc:Unicode>-</pc:Unicode>
                    </pc:TextEquiv>
                </pc:Word>
                <pc:Word id="word-15fc26ac-a04b-4305-b842-83ed27b63797">
                    <pc:Coords points="1910,1731 1950,1732 1951,1766 1910,1765"/>
                    <pc:TextEquiv>
                        <pc:Unicode>ry</pc:Unicode>
                    </pc:TextEquiv>
                </pc:Word>
                <pc:Word id="word-b04c8ee3-8686-4eb2-ae18-58bfbbc8e2a6">
                    <pc:Coords points="1987,1727 2058,1727 2059,1763 1987,1762"/>
                    <pc:TextEquiv>
                        <pc:Unicode>not,</pc:Unicode>
                    </pc:TextEquiv>
                </pc:Word>
                <pc:Word id="word-84438243-e3d4-4c8b-9953-51ff7395f139">
                    <pc:Coords points="2116,1729 2250,1730 2251,1769 2117,1768"/>
                    <pc:TextEquiv>
                        <pc:Unicode>tar - ry</pc:Unicode>
                    </pc:TextEquiv>
                </pc:Word>
                <pc:Word id="word-41bf2718-4ca3-4e90-b40a-a9941b173b4e">
                    <pc:Coords points="2293,1732 2363,1732 2364,1762 2293,1761"/>
                    <pc:TextEquiv>
                        <pc:Unicode>not.</pc:Unicode>
                    </pc:TextEquiv>
                </pc:Word>
                <pc:TextEquiv>
                    <pc:Unicode>tar-ry - not; Bright - er is our home "up there," Tar - ry not, tar - ry not.</pc:Unicode>
                </pc:TextEquiv>
            </pc:TextLine>
        </pc:TextRegion>
    </pc:Page>
</pc:PcGts>
